Workbook
Name diagram_changer: IF('Best Country'!$L$3="Map", 'Best Country (diagrams)'!$A$1:$G$19, 'Best Country (diagrams)'!$A$22:$G$40)

Sheet Best Country
A1: Best Country
A3: Move the sliders to set your priorities | G3: Continent: | H3: Europe | K3: Diagram type: | L3: Map | O3: =G6&" (0-100)" -> Finland (0-100)
A5: Low cost of living (including rent) | G5: According to you, the best country is | K5: Your overall rating (0-100) | O5: Cost of living
A6: =E6 -> 6 | E6: 6 | G6: ='Best Country (help)'!A15 -> Finland | K6: ='Best Country (help)'!B15 -> 73.26 | O6: {=ROUND(_xlfn.XLOOKUP('Best Country (help)'!A15,_xlfn.ANCHORARRAY( 'Best Country (help)'!H5), 'Best Country (help)'!S5:S238)*100, 'Best Country (help)'!B1)} -> 58.67
A8: High income | O8: Income
A9: =E9 -> 7 | E9: 7 | O9: {=ROUND(_xlfn.XLOOKUP('Best Country (help)'!A15,_xlfn.ANCHORARRAY( 'Best Country (help)'!H5), 'Best Country (help)'!Q5:Q238)*100, 'Best Country (help)'!B1)} -> 20.63
A11: Low income inequality | O11: Income inequality
A12: =E12 -> 5 | E12: 5 | O12: {=ROUND(_xlfn.XLOOKUP('Best Country (help)'!A15,_xlfn.ANCHORARRAY( 'Best Country (help)'!H5), 'Best Country (help)'!K5:K238)*100, 'Best Country (help)'!B1)} -> 90.12
A14: High human development | O14: Development
A15: =E15 -> 8 | E15: 8 | O15: {=ROUND(_xlfn.XLOOKUP('Best Country (help)'!A15,_xlfn.ANCHORARRAY( 'Best Country (help)'!H5), 'Best Country (help)'!M5:M238)*100, 'Best Country (help)'!B1)} -> 95.89
A17: High life expectancy | O17: Life Expectancy
A18: =E18 -> 5 | E18: 5 | O18: {=ROUND(_xlfn.XLOOKUP('Best Country (help)'!A15,_xlfn.ANCHORARRAY( 'Best Country (help)'!H5), 'Best Country (help)'!O5:O238)*100, 'Best Country (help)'!B1)} -> 87.85
A20: High safety | O20: Safety
A21: =E21 -> 4 | E21: 4 | O21: {=ROUND(_xlfn.XLOOKUP('Best Country (help)'!A15,_xlfn.ANCHORARRAY( 'Best Country (help)'!H5), 'Best Country (help)'!U5:U238)*100, 'Best Country (help)'!B1)} -> 82.19
A23: Good health care | O23: Health Care
A24: =E24 -> 3 | E24: 3 | O24: {=ROUND(_xlfn.XLOOKUP('Best Country (help)'!A15,_xlfn.ANCHORARRAY( 'Best Country (help)'!H5), 'Best Country (help)'!W5:W238)*100, 'Best Country (help)'!B1)} -> 20.25
A26: High happieness | O26: Happieness
A27: =E27 -> 9 | E27: 9 | O27: {=ROUND(_xlfn.XLOOKUP('Best Country (help)'!A15,_xlfn.ANCHORARRAY( 'Best Country (help)'!H5), 'Best Country (help)'!Y5:Y238)*100, 'Best Country (help)'!B1)} -> 100

Sheet Best Country (help)
A1: Digits to round: | B1: 2 | G1: Continent | H1: Country | I1: Overall rating | J1: Gini | K1: 0-100% | L1: HDI | M1: 0-100% | N1: Life expectancy | O1: 0-100% | P1: GDP per capita | Q1: 0-100% | R1: Cost of living (including rent) | S1: 0-100% | T1: Safety | U1: 0-100% | V1: Health Care | W1: 0-100% | X1: Happieness | Y1: 0-100%
D2: Clean ratings x100 | H2: Max | J2: =MAX(_xlfn.ANCHORARRAY(J5)) -> 0.6302572 | L2: =MAX(_xlfn.ANCHORARRAY(L5)) -> 0.972 | N2: =MAX(_xlfn.ANCHORARRAY(N5)) -> 85.706 | P2: =MAX(_xlfn.ANCHORARRAY(P5)) -> 260696 | R2: =MAX(_xlfn.ANCHORARRAY(R5)) -> 94.3 | T2: =MAX(_xlfn.ANCHORARRAY(T5)) -> 85.2 | V2: =MAX(_xlfn.ANCHORARRAY(V5)) -> 87 | X2: =MAX(_xlfn.ANCHORARRAY(X5)) -> 7.736
A3: Continents | B3: Diagram Type | D3: Country | E3: Rating | H3: Min | J3: =MIN(_xlfn.ANCHORARRAY(J5)) -> 0.24078926 | L3: =MIN(_xlfn.ANCHORARRAY(L5)) -> 0.388 | N3: =MIN(_xlfn.ANCHORARRAY(N5)) -> 54.462 | P3: =MIN(_xlfn.ANCHORARRAY(P5)) -> 328 | R3: =MIN(_xlfn.ANCHORARRAY(R5)) -> 11.3 | T3: =MIN(_xlfn.ANCHORARRAY(T5)) -> 19.5 | V3: =MIN(_xlfn.ANCHORARRAY(V5)) -> 39.6 | X3: =MIN(_xlfn.ANCHORARRAY(X5)) -> 1.364
A5: World | B5: Map | D5: {=_xlfn._xlws.FILTER(_xlfn.ANCHORARRAY(H5), I5:I238<>"")} -> Albania | E5: {=ROUND(_xlfn._xlws.FILTER(I5:I238*100, I5:I238<>""), B1)} -> 62.38 | G5: {=main_table[Continent]} -> Asia | H5: {=main_table[Country]} -> Afghanistan | I5: =IFERROR(( K5*'Best Country'!$E$12+ M5*'Best Country'!$E$15+ O5*'Best Country'!$E$18+ Q5*'Best Country'!$E$9+ S5*'Best Country'!$E$6+ U5*'Best Country'!$E$21+ W5*'Best Country'!$E$24+ Y5*'Best Country'!$E$27 )/SUM('Best Country'!$E$5:$E$28), "") | J5: {=IF(main_table[Gini-Coefficient (2021 prices; income or consumption consolid)]<>0, main_table[Gini-Coefficient (2021 prices; income or consumption consolid)], "")} | K5: =IFERROR(1-(J5-J$3)/(J$2-J$3), "") | L5: {=IF(main_table[HDI (2023)]<>0, main_table[HDI (2023)], "")} -> 0.496 | M5: =IFERROR((L5-L$3)/(L$2-L$3), "") -> 0.18493151 | N5: {=IF(main_table[Years of life expectancy at birth (2023)]<>0, main_table[Years of life expectancy at birth (2023)], "")} -> 66.035 | O5: =IFERROR((N5-N$3)/(N$2-N$3), "") -> 0.37040712 | P5: {=IF(main_table[GDP per capita (USD)]<>0, main_table[GDP per capita (USD)], "")} -> 374 | Q5: =IFERROR((P5-P$3)/(P$2-P$3), "") -> 0.00017667302 | R5: {=IF(main_table[Cost of Living Plus Rent Index]<>0, main_table[Cost of Living Plus Rent Index], "")} -> 11.6 | S5: =IFERROR(1-(R5-R$3)/(R$2-R$3), "") -> 0.99638554 | T5: {=IF(main_table[Safety Index], main_table[Safety Index], "")} | U5: =IFERROR((T5-T$3)/(T$2-T$3), "") | V5: {=IF(main_table[Health Care Index]<>0, main_table[Health Care Index], "")} | W5: =IFERROR(1-(V5-V$3)/(V$2-V$3), "") | X5: {=IF(main_table[Word Happieness Report (life evaluation; 3-year-average)]<>0, main_table[Word Happieness Report (life evaluation; 3-year-average)], "")} -> 1.364 | Y5: =IFERROR((X5-X$3)/(X$2-X$3), "") -> 0
A6: Africa | B6: Bars | D6: Argentina | E6: 58.52 | G6: Europe | H6: Albania | I6: =IFERROR(( K6*'Best Country'!$E$12+ M6*'Best Country'!$E$15+ O6*'Best Country'!$E$18+ Q6*'Best Country'!$E$9+ S6*'Best Country'!$E$6+ U6*'Best Country'!$E$21+ W6*'Best Country'!$E$24+ Y6*'Best Country'!$E$27 )/SUM('Best Country'!$E$5:$E$28), "") -> 0.62384718 | J6: 0.2941963 | K6: =IFERROR(1-(J6-J$3)/(J$2-J$3), "") -> 0.86287179 | L6: 0.81 | M6: =IFERROR((L6-L$3)/(L$2-L$3), "") -> 0.72260274 | N6: 79.602 | O6: =IFERROR((N6-N$3)/(N$2-N$3), "") -> 0.80463449 | P6: 10237 | Q6: =IFERROR((P6-P$3)/(P$2-P$3), "") -> 0.038057672 | R6: 31.3 | S6: =IFERROR(1-(R6-R$3)/(R$2-R$3), "") -> 0.75903614 | T6: 55.8 | U6: =IFERROR((T6-T$3)/(T$2-T$3), "") -> 0.55251142 | V6: 48.2 | W6: =IFERROR(1-(V6-V$3)/(V$2-V$3), "") -> 0.8185654 | X6: 5.411 | Y6: =IFERROR((X6-X$3)/(X$2-X$3), "") -> 0.63512241
A7: Asia | D7: Armenia | E7: 63.35 | G7: Africa | H7: Algeria | I7: =IFERROR(( K7*'Best Country'!$E$12+ M7*'Best Country'!$E$15+ O7*'Best Country'!$E$18+ Q7*'Best Country'!$E$9+ S7*'Best Country'!$E$6+ U7*'Best Country'!$E$21+ W7*'Best Country'!$E$24+ Y7*'Best Country'!$E$27 )/SUM('Best Country'!$E$5:$E$28), "") | J7: 0.27615732 | K7: =IFERROR(1-(J7-J$3)/(J$2-J$3), "") -> 0.90918878 | L7: 0.763 | M7: =IFERROR((L7-L$3)/(L$2-L$3), "") -> 0.64212329 | N7: 76.261 | O7: =IFERROR((N7-N$3)/(N$2-N$3), "") -> 0.69770196 | P7: 5668 | Q7: =IFERROR((P7-P$3)/(P$2-P$3), "") -> 0.020509433 | R7: 16.7 | S7: =IFERROR(1-(R7-R$3)/(R$2-R$3), "") -> 0.93493976 | U7: =IFERROR((T7-T$3)/(T$2-T$3), "") | W7: =IFERROR(1-(V7-V$3)/(V$2-V$3), "") | X7: 5.571 | Y7: =IFERROR((X7-X$3)/(X$2-X$3), "") -> 0.66023227
A8: Europe | D8: Australia | E8: 68.13 | G8: Oceania | H8: American Samoa | I8: =IFERROR(( K8*'Best Country'!$E$12+ M8*'Best Country'!$E$15+ O8*'Best Country'!$E$18+ Q8*'Best Country'!$E$9+ S8*'Best Country'!$E$6+ U8*'Best Country'!$E$21+ W8*'Best Country'!$E$24+ Y8*'Best Country'!$E$27 )/SUM('Best Country'!$E$5:$E$28), "") | K8: =IFERROR(1-(J8-J$3)/(J$2-J$3), "") | M8: =IFERROR((L8-L$3)/(L$2-L$3), "") | O8: =IFERROR((N8-N$3)/(N$2-N$3), "") | Q8: =IFERROR((P8-P$3)/(P$2-P$3), "") | S8: =IFERROR(1-(R8-R$3)/(R$2-R$3), "") | U8: =IFERROR((T8-T$3)/(T$2-T$3), "") | W8: =IFERROR(1-(V8-V$3)/(V$2-V$3), "") | Y8: =IFERROR((X8-X$3)/(X$2-X$3), "")
A9: North America | D9: Austria | E9: 68.5 | G9: Europe | H9: Andorra | I9: =IFERROR(( K9*'Best Country'!$E$12+ M9*'Best Country'!$E$15+ O9*'Best Country'!$E$18+ Q9*'Best Country'!$E$9+ S9*'Best Country'!$E$6+ U9*'Best Country'!$E$21+ W9*'Best Country'!$E$24+ Y9*'Best Country'!$E$27 )/SUM('Best Country'!$E$5:$E$28), "") | K9: =IFERROR(1-(J9-J$3)/(J$2-J$3), "") | L9: 0.913 | M9: =IFERROR((L9-L$3)/(L$2-L$3), "") -> 0.8989726 | N9: 84.041 | O9: =IFERROR((N9-N$3)/(N$2-N$3), "") -> 0.94670977 | P9: 48671 | Q9: =IFERROR((P9-P$3)/(P$2-P$3), "") -> 0.18567182 | S9: =IFERROR(1-(R9-R$3)/(R$2-R$3), "") | U9: =IFERROR((T9-T$3)/(T$2-T$3), "") | W9: =IFERROR(1-(V9-V$3)/(V$2-V$3), "") | Y9: =IFERROR((X9-X$3)/(X$2-X$3), "")
A10: Oceania | D10: Bangladesh | E10: 52.31 | G10: Africa | H10: Angola | I10: =IFERROR(( K10*'Best Country'!$E$12+ M10*'Best Country'!$E$15+ O10*'Best Country'!$E$18+ Q10*'Best Country'!$E$9+ S10*'Best Country'!$E$6+ U10*'Best Country'!$E$21+ W10*'Best Country'!$E$24+ Y10*'Best Country'!$E$27 )/SUM('Best Country'!$E$5:$E$28), "") | J10: 0.51264286 | K10: =IFERROR(1-(J10-J$3)/(J$2-J$3), "") -> 0.30198722 | L10: 0.616 | M10: =IFERROR((L10-L$3)/(L$2-L$3), "") -> 0.39041096 | N10: 64.617 | O10: =IFERROR((N10-N$3)/(N$2-N$3), "") -> 0.3250224 | P10: 2903 | Q10: =IFERROR((P10-P$3)/(P$2-P$3), "") -> 0.0098898482 | S10: =IFERROR(1-(R10-R$3)/(R$2-R$3), "") | U10: =IFERROR((T10-T$3)/(T$2-T$3), "") | W10: =IFERROR(1-(V10-V$3)/(V$2-V$3), "") | Y10: =IFERROR((X10-X$3)/(X$2-X$3), "")
A11: South America | D11: Belgium | E11: 68.78 | G11: North America | H11: Anguilla | I11: =IFERROR(( K11*'Best Country'!$E$12+ M11*'Best Country'!$E$15+ O11*'Best Country'!$E$18+ Q11*'Best Country'!$E$9+ S11*'Best Country'!$E$6+ U11*'Best Country'!$E$21+ W11*'Best Country'!$E$24+ Y11*'Best Country'!$E$27 )/SUM('Best Country'!$E$5:$E$28), "") | K11: =IFERROR(1-(J11-J$3)/(J$2-J$3), "") | M11: =IFERROR((L11-L$3)/(L$2-L$3), "") | O11: =IFERROR((N11-N$3)/(N$2-N$3), "") | P11: 28228 | Q11: =IFERROR((P11-P$3)/(P$2-P$3), "") -> 0.10715603 | S11: =IFERROR(1-(R11-R$3)/(R$2-R$3), "") | U11: =IFERROR((T11-T$3)/(T$2-T$3), "") | W11: =IFERROR(1-(V11-V$3)/(V$2-V$3), "") | Y11: =IFERROR((X11-X$3)/(X$2-X$3), "")
D12: Bosnia and Herzegovina | E12: 63.45 | G12: North America | H12: Antigua and Barbuda | I12: =IFERROR(( K12*'Best Country'!$E$12+ M12*'Best Country'!$E$15+ O12*'Best Country'!$E$18+ Q12*'Best Country'!$E$9+ S12*'Best Country'!$E$6+ U12*'Best Country'!$E$21+ W12*'Best Country'!$E$24+ Y12*'Best Country'!$E$27 )/SUM('Best Country'!$E$5:$E$28), "") | K12: =IFERROR(1-(J12-J$3)/(J$2-J$3), "") | L12: 0.851 | M12: =IFERROR((L12-L$3)/(L$2-L$3), "") -> 0.79280822 | N12: 77.598 | O12: =IFERROR((N12-N$3)/(N$2-N$3), "") -> 0.74049417 | P12: 25189 | Q12: =IFERROR((P12-P$3)/(P$2-P$3), "") -> 0.095484084 | S12: =IFERROR(1-(R12-R$3)/(R$2-R$3), "") | U12: =IFERROR((T12-T$3)/(T$2-T$3), "") | W12: =IFERROR(1-(V12-V$3)/(V$2-V$3), "") | Y12: =IFERROR((X12-X$3)/(X$2-X$3), "")
D13: Brazil | E13: 55.29 | G13: South America | H13: Argentina | I13: =IFERROR(( K13*'Best Country'!$E$12+ M13*'Best Country'!$E$15+ O13*'Best Country'!$E$18+ Q13*'Best Country'!$E$9+ S13*'Best Country'!$E$6+ U13*'Best Country'!$E$21+ W13*'Best Country'!$E$24+ Y13*'Best Country'!$E$27 )/SUM('Best Country'!$E$5:$E$28), "") -> 0.58519334 | J13: 0.42390975 | K13: =IFERROR(1-(J13-J$3)/(J$2-J$3), "") -> 0.52981883 | L13: 0.865 | M13: =IFERROR((L13-L$3)/(L$2-L$3), "") -> 0.81678082 | N13: 77.395 | O13: =IFERROR((N13-N$3)/(N$2-N$3), "") -> 0.73399693 | P13: 14908 | Q13: =IFERROR((P13-P$3)/(P$2-P$3), "") -> 0.055997665 | R13: 26.6 | S13: =IFERROR(1-(R13-R$3)/(R$2-R$3), "") -> 0.81566265 | T13: 36.7 | U13: =IFERROR((T13-T$3)/(T$2-T$3), "") -> 0.26179604 | V13: 67.9 | W13: =IFERROR(1-(V13-V$3)/(V$2-V$3), "") -> 0.40295359 | X13: 6.397 | Y13: =IFERROR((X13-X$3)/(X$2-X$3), "") -> 0.7898619
A14: Top Country | B14: Top Rating | D14: Bulgaria | E14: 60.84 | G14: Asia | H14: Armenia | I14: =IFERROR(( K14*'Best Country'!$E$12+ M14*'Best Country'!$E$15+ O14*'Best Country'!$E$18+ Q14*'Best Country'!$E$9+ S14*'Best Country'!$E$6+ U14*'Best Country'!$E$21+ W14*'Best Country'!$E$24+ Y14*'Best Country'!$E$27 )/SUM('Best Country'!$E$5:$E$28), "") -> 0.6335177 | J14: 0.2715465 | K14: =IFERROR(1-(J14-J$3)/(J$2-J$3), "") -> 0.92102754 | L14: 0.811 | M14: =IFERROR((L14-L$3)/(L$2-L$3), "") -> 0.72431507 | N14: 75.683 | O14: =IFERROR((N14-N$3)/(N$2-N$3), "") -> 0.67920241 | P14: 8894 | Q14: =IFERROR((P14-P$3)/(P$2-P$3), "") -> 0.032899588 | R14: 29.7 | S14: =IFERROR(1-(R14-R$3)/(R$2-R$3), "") -> 0.77831325 | T14: 77.6 | U14: =IFERROR((T14-T$3)/(T$2-T$3), "") -> 0.88432268 | V14: 60 | W14: =IFERROR(1-(V14-V$3)/(V$2-V$3), "") -> 0.56962025 | X14: 5.494 | Y14: =IFERROR((X14-X$3)/(X$2-X$3), "") -> 0.64814815
A15: {=_xlfn.XLOOKUP(B15,_xlfn.ANCHORARRAY( B37),_xlfn.ANCHORARRAY( A37))} -> Finland | B15: =MAX(_xlfn.ANCHORARRAY(B37)) -> 73.26 | D15: Canada | E15: 68.29 | G15: North America | H15: Aruba | I15: =IFERROR(( K15*'Best Country'!$E$12+ M15*'Best Country'!$E$15+ O15*'Best Country'!$E$18+ Q15*'Best Country'!$E$9+ S15*'Best Country'!$E$6+ U15*'Best Country'!$E$21+ W15*'Best Country'!$E$24+ Y15*'Best Country'!$E$27 )/SUM('Best Country'!$E$5:$E$28), "") | K15: =IFERROR(1-(J15-J$3)/(J$2-J$3), "") | M15: =IFERROR((L15-L$3)/(L$2-L$3), "") | O15: =IFERROR((N15-N$3)/(N$2-N$3), "") | P15: 37911 | Q15: =IFERROR((P15-P$3)/(P$2-P$3), "") -> 0.1443457 | S15: =IFERROR(1-(R15-R$3)/(R$2-R$3), "") | U15: =IFERROR((T15-T$3)/(T$2-T$3), "") | W15: =IFERROR(1-(V15-V$3)/(V$2-V$3), "") | Y15: =IFERROR((X15-X$3)/(X$2-X$3), "")
D16: Chile | E16: 61.19 | G16: Oceania | H16: Australia | I16: =IFERROR(( K16*'Best Country'!$E$12+ M16*'Best Country'!$E$15+ O16*'Best Country'!$E$18+ Q16*'Best Country'!$E$9+ S16*'Best Country'!$E$6+ U16*'Best Country'!$E$21+ W16*'Best Country'!$E$24+ Y16*'Best Country'!$E$27 )/SUM('Best Country'!$E$5:$E$28), "") -> 0.68129345 | J16: 0.34332526 | K16: =IFERROR(1-(J16-J$3)/(J$2-J$3), "") -> 0.73672801 | L16: 0.958 | M16: =IFERROR((L16-L$3)/(L$2-L$3), "") -> 0.9760274 | N16: 83.923 | O16: =IFERROR((N16-N$3)/(N$2-N$3), "") -> 0.94293304 | P16: 65681 | Q16: =IFERROR((P16-P$3)/(P$2-P$3), "") -> 0.25100243 | R16: 49.5 | S16: =IFERROR(1-(R16-R$3)/(R$2-R$3), "") -> 0.53975904 | T16: 52.6 | U16: =IFERROR((T16-T$3)/(T$2-T$3), "") -> 0.50380518 | V16: 73.1 | W16: =IFERROR(1-(V16-V$3)/(V$2-V$3), "") -> 0.29324895 | X16: 6.974 | Y16: =IFERROR((X16-X$3)/(X$2-X$3), "") -> 0.88041431
D17: China | E17: 62.92 | G17: Europe | H17: Austria | I17: =IFERROR(( K17*'Best Country'!$E$12+ M17*'Best Country'!$E$15+ O17*'Best Country'!$E$18+ Q17*'Best Country'!$E$9+ S17*'Best Country'!$E$6+ U17*'Best Country'!$E$21+ W17*'Best Country'!$E$24+ Y17*'Best Country'!$E$27 )/SUM('Best Country'!$E$5:$E$28), "") -> 0.68495204 | J17: 0.3089293 | K17: =IFERROR(1-(J17-J$3)/(J$2-J$3), "") -> 0.82504326 | L17: 0.93 | M17: =IFERROR((L17-L$3)/(L$2-L$3), "") -> 0.92808219 | N17: 81.956 | O17: =IFERROR((N17-N$3)/(N$2-N$3), "") -> 0.87997696 | P17: 58627 | Q17: =IFERROR((P17-P$3)/(P$2-P$3), "") -> 0.22391 | R17: 49.1 | S17: =IFERROR(1-(R17-R$3)/(R$2-R$3), "") -> 0.54457831 | T17: 71.7 | U17: =IFERROR((T17-T$3)/(T$2-T$3), "") -> 0.79452055 | V17: 78.5 | W17: =IFERROR(1-(V17-V$3)/(V$2-V$3), "") -> 0.17932489 | X17: 6.81 | Y17: =IFERROR((X17-X$3)/(X$2-X$3), "") -> 0.85467671
A18: Top 10 sorted | D18: Colombia | E18: 52.87 | G18: Asia | H18: Azerbaijan | I18: =IFERROR(( K18*'Best Country'!$E$12+ M18*'Best Country'!$E$15+ O18*'Best Country'!$E$18+ Q18*'Best Country'!$E$9+ S18*'Best Country'!$E$6+ U18*'Best Country'!$E$21+ W18*'Best Country'!$E$24+ Y18*'Best Country'!$E$27 )/SUM('Best Country'!$E$5:$E$28), "") | K18: =IFERROR(1-(J18-J$3)/(J$2-J$3), "") | L18: 0.789 | M18: =IFERROR((L18-L$3)/(L$2-L$3), "") -> 0.68664384 | N18: 74.429 | O18: =IFERROR((N18-N$3)/(N$2-N$3), "") -> 0.6390667 | P18: 7585 | Q18: =IFERROR((P18-P$3)/(P$2-P$3), "") -> 0.027872089 | R18: 20.7 | S18: =IFERROR(1-(R18-R$3)/(R$2-R$3), "") -> 0.88674699 | T18: 68.2 | U18: =IFERROR((T18-T$3)/(T$2-T$3), "") -> 0.7412481 | V18: 49.1 | W18: =IFERROR(1-(V18-V$3)/(V$2-V$3), "") -> 0.79957806 | X18: 4.875 | Y18: =IFERROR((X18-X$3)/(X$2-X$3), "") -> 0.55100439
A19: Country | B19: Rating | D19: Costa Rica | E19: 60.81 | G19: North America | H19: Bahamas | I19: =IFERROR(( K19*'Best Country'!$E$12+ M19*'Best Country'!$E$15+ O19*'Best Country'!$E$18+ Q19*'Best Country'!$E$9+ S19*'Best Country'!$E$6+ U19*'Best Country'!$E$21+ W19*'Best Country'!$E$24+ Y19*'Best Country'!$E$27 )/SUM('Best Country'!$E$5:$E$28), "") | K19: =IFERROR(1-(J19-J$3)/(J$2-J$3), "") | L19: 0.82 | M19: =IFERROR((L19-L$3)/(L$2-L$3), "") -> 0.73972603 | N19: 74.552 | O19: =IFERROR((N19-N$3)/(N$2-N$3), "") -> 0.64300346 | P19: 37659 | Q19: =IFERROR((P19-P$3)/(P$2-P$3), "") -> 0.14337783 | R19: 68.7 | S19: =IFERROR(1-(R19-R$3)/(R$2-R$3), "") -> 0.30843373 | U19: =IFERROR((T19-T$3)/(T$2-T$3), "") | W19: =IFERROR(1-(V19-V$3)/(V$2-V$3), "") | Y19: =IFERROR((X19-X$3)/(X$2-X$3), "")
A20: {=_xlfn.XLOOKUP(_xlfn.ANCHORARRAY(B20),_xlfn.ANCHORARRAY( B37),_xlfn.ANCHORARRAY( A37))} -> Poland | B20: {=_xlfn.TAKE(_xlfn._xlws.SORT(_xlfn.ANCHORARRAY(B37), 1, 1), -10)} -> 70.16 | D20: Croatia | E20: 66.07 | G20: Asia | H20: Bahrain | I20: =IFERROR(( K20*'Best Country'!$E$12+ M20*'Best Country'!$E$15+ O20*'Best Country'!$E$18+ Q20*'Best Country'!$E$9+ S20*'Best Country'!$E$6+ U20*'Best Country'!$E$21+ W20*'Best Country'!$E$24+ Y20*'Best Country'!$E$27 )/SUM('Best Country'!$E$5:$E$28), "") | K20: =IFERROR(1-(J20-J$3)/(J$2-J$3), "") | L20: 0.899 | M20: =IFERROR((L20-L$3)/(L$2-L$3), "") -> 0.875 | N20: 81.284 | O20: =IFERROR((N20-N$3)/(N$2-N$3), "") -> 0.85846883 | P20: 29105 | Q20: =IFERROR((P20-P$3)/(P$2-P$3), "") -> 0.11052433 | R20: 35.2 | S20: =IFERROR(1-(R20-R$3)/(R$2-R$3), "") -> 0.71204819 | U20: =IFERROR((T20-T$3)/(T$2-T$3), "") | W20: =IFERROR(1-(V20-V$3)/(V$2-V$3), "") | X20: 6.03 | Y20: =IFERROR((X20-X$3)/(X$2-X$3), "") -> 0.73226616
A21: Sweden | B21: 70.59 | D21: Cyprus | E21: 66.74 | G21: Asia | H21: Bangladesh | I21: =IFERROR(( K21*'Best Country'!$E$12+ M21*'Best Country'!$E$15+ O21*'Best Country'!$E$18+ Q21*'Best Country'!$E$9+ S21*'Best Country'!$E$6+ U21*'Best Country'!$E$21+ W21*'Best Country'!$E$24+ Y21*'Best Country'!$E$27 )/SUM('Best Country'!$E$5:$E$28), "") -> 0.52310361 | J21: 0.33373156 | K21: =IFERROR(1-(J21-J$3)/(J$2-J$3), "") -> 0.76136085 | L21: 0.685 | M21: =IFERROR((L21-L$3)/(L$2-L$3), "") -> 0.50856164 | N21: 74.672 | O21: =IFERROR((N21-N$3)/(N$2-N$3), "") -> 0.64684419 | P21: 2659 | Q21: =IFERROR((P21-P$3)/(P$2-P$3), "") -> 0.0089527131 | R21: 13 | S21: =IFERROR(1-(R21-R$3)/(R$2-R$3), "") -> 0.97951807 | T21: 38.5 | U21: =IFERROR((T21-T$3)/(T$2-T$3), "") -> 0.2891933 | V21: 41.7 | W21: =IFERROR(1-(V21-V$3)/(V$2-V$3), "") -> 0.9556962 | X21: 3.851 | Y21: =IFERROR((X21-X$3)/(X$2-X$3), "") -> 0.39030132
A22: Luxembourg | B22: 70.86 | D22: Czech Republic | E22: 69.85 | G22: North America | H22: Barbados | I22: =IFERROR(( K22*'Best Country'!$E$12+ M22*'Best Country'!$E$15+ O22*'Best Country'!$E$18+ Q22*'Best Country'!$E$9+ S22*'Best Country'!$E$6+ U22*'Best Country'!$E$21+ W22*'Best Country'!$E$24+ Y22*'Best Country'!$E$27 )/SUM('Best Country'!$E$5:$E$28), "") | J22: 0.34068036 | K22: =IFERROR(1-(J22-J$3)/(J$2-J$3), "") -> 0.74351907 | L22: 0.811 | M22: =IFERROR((L22-L$3)/(L$2-L$3), "") -> 0.72431507 | N22: 76.178 | O22: =IFERROR((N22-N$3)/(N$2-N$3), "") -> 0.69504545 | P22: 26721 | Q22: =IFERROR((P22-P$3)/(P$2-P$3), "") -> 0.10136806 | S22: =IFERROR(1-(R22-R$3)/(R$2-R$3), "") | U22: =IFERROR((T22-T$3)/(T$2-T$3), "") | W22: =IFERROR(1-(V22-V$3)/(V$2-V$3), "") | Y22: =IFERROR((X22-X$3)/(X$2-X$3), "")
A23: Netherlands | B23: 71.98 | D23: Denmark | E23: 72.46 | G23: Europe | H23: Belarus | I23: =IFERROR(( K23*'Best Country'!$E$12+ M23*'Best Country'!$E$15+ O23*'Best Country'!$E$18+ Q23*'Best Country'!$E$9+ S23*'Best Country'!$E$6+ U23*'Best Country'!$E$21+ W23*'Best Country'!$E$24+ Y23*'Best Country'!$E$27 )/SUM('Best Country'!$E$5:$E$28), "") | J23: 0.24383356 | K23: =IFERROR(1-(J23-J$3)/(J$2-J$3), "") -> 0.99218344 | L23: 0.824 | M23: =IFERROR((L23-L$3)/(L$2-L$3), "") -> 0.74657534 | N23: 74.434 | O23: =IFERROR((N23-N$3)/(N$2-N$3), "") -> 0.63922673 | P23: 7953 | Q23: =IFERROR((P23-P$3)/(P$2-P$3), "") -> 0.029285473 | R23: 18.4 | S23: =IFERROR(1-(R23-R$3)/(R$2-R$3), "") -> 0.91445783 | T23: 50.9 | U23: =IFERROR((T23-T$3)/(T$2-T$3), "") -> 0.47792998 | V23: 49.3 | W23: =IFERROR(1-(V23-V$3)/(V$2-V$3), "") -> 0.79535865 | Y23: =IFERROR((X23-X$3)/(X$2-X$3), "")
A24: Denmark | B24: 72.46 | D24: Ecuador | E24: 53.33 | G24: Europe | H24: Belgium | I24: =IFERROR(( K24*'Best Country'!$E$12+ M24*'Best Country'!$E$15+ O24*'Best Country'!$E$18+ Q24*'Best Country'!$E$9+ S24*'Best Country'!$E$6+ U24*'Best Country'!$E$21+ W24*'Best Country'!$E$24+ Y24*'Best Country'!$E$27 )/SUM('Best Country'!$E$5:$E$28), "") -> 0.68783501 | J24: 0.26375556 | K24: =IFERROR(1-(J24-J$3)/(J$2-J$3), "") -> 0.9410316 | L24: 0.951 | M24: =IFERROR((L24-L$3)/(L$2-L$3), "") -> 0.9640411 | N24: 82.115 | O24: =IFERROR((N24-N$3)/(N$2-N$3), "") -> 0.88506593 | P24: 58244 | Q24: =IFERROR((P24-P$3)/(P$2-P$3), "") -> 0.22243901 | R24: 45.9 | S24: =IFERROR(1-(R24-R$3)/(R$2-R$3), "") -> 0.58313253 | T24: 50.5 | U24: =IFERROR((T24-T$3)/(T$2-T$3), "") -> 0.4718417 | V24: 75.8 | W24: =IFERROR(1-(V24-V$3)/(V$2-V$3), "") -> 0.23628692 | X24: 6.91 | Y24: =IFERROR((X24-X$3)/(X$2-X$3), "") -> 0.87037037
A25: Ireland | B25: 72.6 | D25: Egypt | E25: 55.68 | G25: North America | H25: Belize | I25: =IFERROR(( K25*'Best Country'!$E$12+ M25*'Best Country'!$E$15+ O25*'Best Country'!$E$18+ Q25*'Best Country'!$E$9+ S25*'Best Country'!$E$6+ U25*'Best Country'!$E$21+ W25*'Best Country'!$E$24+ Y25*'Best Country'!$E$27 )/SUM('Best Country'!$E$5:$E$28), "") | J25: 0.39949584 | K25: =IFERROR(1-(J25-J$3)/(J$2-J$3), "") -> 0.59250412 | L25: 0.721 | M25: =IFERROR((L25-L$3)/(L$2-L$3), "") -> 0.57020548 | N25: 73.566 | O25: =IFERROR((N25-N$3)/(N$2-N$3), "") -> 0.6114454 | P25: 8538 | Q25: =IFERROR((P25-P$3)/(P$2-P$3), "") -> 0.031532293 | R25: 28.3 | S25: =IFERROR(1-(R25-R$3)/(R$2-R$3), "") -> 0.79518072 | U25: =IFERROR((T25-T$3)/(T$2-T$3), "") | W25: =IFERROR(1-(V25-V$3)/(V$2-V$3), "") | X25: 6.711 | Y25: =IFERROR((X25-X$3)/(X$2-X$3), "") -> 0.83913999
A26: Iceland | B26: 72.73 | D26: Estonia | E26: 66.57 | G26: Africa | H26: Benin | I26: =IFERROR(( K26*'Best Country'!$E$12+ M26*'Best Country'!$E$15+ O26*'Best Country'!$E$18+ Q26*'Best Country'!$E$9+ S26*'Best Country'!$E$6+ U26*'Best Country'!$E$21+ W26*'Best Country'!$E$24+ Y26*'Best Country'!$E$27 )/SUM('Best Country'!$E$5:$E$28), "") | J26: 0.34395808 | K26: =IFERROR(1-(J26-J$3)/(J$2-J$3), "") -> 0.73510318 | L26: 0.515 | M26: =IFERROR((L26-L$3)/(L$2-L$3), "") -> 0.21746575 | N26: 60.774 | O26: =IFERROR((N26-N$3)/(N$2-N$3), "") -> 0.20202279 | P26: 1501 | Q26: =IFERROR((P26-P$3)/(P$2-P$3), "") -> 0.0045051619 | S26: =IFERROR(1-(R26-R$3)/(R$2-R$3), "") | U26: =IFERROR((T26-T$3)/(T$2-T$3), "") | W26: =IFERROR(1-(V26-V$3)/(V$2-V$3), "") | X26: 4.357 | Y26: =IFERROR((X26-X$3)/(X$2-X$3), "") -> 0.46971124
A27: Slovenia | B27: 72.75 | D27: Finland | E27: 73.26 | G27: North America | H27: Bermuda | I27: =IFERROR(( K27*'Best Country'!$E$12+ M27*'Best Country'!$E$15+ O27*'Best Country'!$E$18+ Q27*'Best Country'!$E$9+ S27*'Best Country'!$E$6+ U27*'Best Country'!$E$21+ W27*'Best Country'!$E$24+ Y27*'Best Country'!$E$27 )/SUM('Best Country'!$E$5:$E$28), "") | K27: =IFERROR(1-(J27-J$3)/(J$2-J$3), "") | M27: =IFERROR((L27-L$3)/(L$2-L$3), "") | O27: =IFERROR((N27-N$3)/(N$2-N$3), "") | P27: 126120 | Q27: =IFERROR((P27-P$3)/(P$2-P$3), "") -> 0.48313157 | S27: =IFERROR(1-(R27-R$3)/(R$2-R$3), "") | U27: =IFERROR((T27-T$3)/(T$2-T$3), "") | W27: =IFERROR(1-(V27-V$3)/(V$2-V$3), "") | Y27: =IFERROR((X27-X$3)/(X$2-X$3), "")
A28: Norway | B28: 72.93 | D28: France | E28: 64.44 | G28: Asia | H28: Bhutan | I28: =IFERROR(( K28*'Best Country'!$E$12+ M28*'Best Country'!$E$15+ O28*'Best Country'!$E$18+ Q28*'Best Country'!$E$9+ S28*'Best Country'!$E$6+ U28*'Best Country'!$E$21+ W28*'Best Country'!$E$24+ Y28*'Best Country'!$E$27 )/SUM('Best Country'!$E$5:$E$28), "") | J28: 0.2845992 | K28: =IFERROR(1-(J28-J$3)/(J$2-J$3), "") -> 0.88751336 | L28: 0.698 | M28: =IFERROR((L28-L$3)/(L$2-L$3), "") -> 0.53082192 | N28: 72.975 | O28: =IFERROR((N28-N$3)/(N$2-N$3), "") -> 0.59252977 | P28: 4295 | Q28: =IFERROR((P28-P$3)/(P$2-P$3), "") -> 0.015236127 | S28: =IFERROR(1-(R28-R$3)/(R$2-R$3), "") | U28: =IFERROR((T28-T$3)/(T$2-T$3), "") | W28: =IFERROR(1-(V28-V$3)/(V$2-V$3), "") | Y28: =IFERROR((X28-X$3)/(X$2-X$3), "")
A29: Finland | B29: 73.26 | D29: Georgia | E29: 62.59 | G29: South America | H29: Bolivia | I29: =IFERROR(( K29*'Best Country'!$E$12+ M29*'Best Country'!$E$15+ O29*'Best Country'!$E$18+ Q29*'Best Country'!$E$9+ S29*'Best Country'!$E$6+ U29*'Best Country'!$E$21+ W29*'Best Country'!$E$24+ Y29*'Best Country'!$E$27 )/SUM('Best Country'!$E$5:$E$28), "") | J29: 0.42050114 | K29: =IFERROR(1-(J29-J$3)/(J$2-J$3), "") -> 0.5385708 | L29: 0.733 | M29: =IFERROR((L29-L$3)/(L$2-L$3), "") -> 0.59075342 | N29: 68.581 | O29: =IFERROR((N29-N$3)/(N$2-N$3), "") -> 0.45189476 | P29: 4478 | Q29: =IFERROR((P29-P$3)/(P$2-P$3), "") -> 0.015938979 | R29: 18.1 | S29: =IFERROR(1-(R29-R$3)/(R$2-R$3), "") -> 0.91807229 | U29: =IFERROR((T29-T$3)/(T$2-T$3), "") | W29: =IFERROR(1-(V29-V$3)/(V$2-V$3), "") | X29: 5.868 | Y29: =IFERROR((X29-X$3)/(X$2-X$3), "") -> 0.70684244
D30: Germany | E30: 68.11 | G30: Europe | H30: Bosnia and Herzegovina | I30: =IFERROR(( K30*'Best Country'!$E$12+ M30*'Best Country'!$E$15+ O30*'Best Country'!$E$18+ Q30*'Best Country'!$E$9+ S30*'Best Country'!$E$6+ U30*'Best Country'!$E$21+ W30*'Best Country'!$E$24+ Y30*'Best Country'!$E$27 )/SUM('Best Country'!$E$5:$E$28), "") -> 0.63446473 | J30: 0.33030185 | K30: =IFERROR(1-(J30-J$3)/(J$2-J$3), "") -> 0.77016699 | L30: 0.804 | M30: =IFERROR((L30-L$3)/(L$2-L$3), "") -> 0.71232877 | N30: 77.85 | O30: =IFERROR((N30-N$3)/(N$2-N$3), "") -> 0.74855972 | P30: 9174 | Q30: =IFERROR((P30-P$3)/(P$2-P$3), "") -> 0.033974989 | R30: 23.4 | S30: =IFERROR(1-(R30-R$3)/(R$2-R$3), "") -> 0.85421687 | T30: 58.8 | U30: =IFERROR((T30-T$3)/(T$2-T$3), "") -> 0.59817352 | V30: 54.9 | W30: =IFERROR(1-(V30-V$3)/(V$2-V$3), "") -> 0.67721519 | X30: 6.136 | Y30: =IFERROR((X30-X$3)/(X$2-X$3), "") -> 0.74890144
D31: Greece | E31: 64.83 | G31: Africa | H31: Botswana | I31: =IFERROR(( K31*'Best Country'!$E$12+ M31*'Best Country'!$E$15+ O31*'Best Country'!$E$18+ Q31*'Best Country'!$E$9+ S31*'Best Country'!$E$6+ U31*'Best Country'!$E$21+ W31*'Best Country'!$E$24+ Y31*'Best Country'!$E$27 )/SUM('Best Country'!$E$5:$E$28), "") | J31: 0.5490736 | K31: =IFERROR(1-(J31-J$3)/(J$2-J$3), "") -> 0.20844745 | L31: 0.731 | M31: =IFERROR((L31-L$3)/(L$2-L$3), "") -> 0.58732877 | N31: 69.163 | O31: =IFERROR((N31-N$3)/(N$2-N$3), "") -> 0.47052234 | P31: 7572 | Q31: =IFERROR((P31-P$3)/(P$2-P$3), "") -> 0.027822159 | R31: 26.2 | S31: =IFERROR(1-(R31-R$3)/(R$2-R$3), "") -> 0.82048193 | U31: =IFERROR((T31-T$3)/(T$2-T$3), "") | W31: =IFERROR(1-(V31-V$3)/(V$2-V$3), "") | X31: 3.438 | Y31: =IFERROR((X31-X$3)/(X$2-X$3), "") -> 0.3254865
D32: Hungary | E32: 66.17 | G32: South America | H32: Brazil | I32: =IFERROR(( K32*'Best Country'!$E$12+ M32*'Best Country'!$E$15+ O32*'Best Country'!$E$18+ Q32*'Best Country'!$E$9+ S32*'Best Country'!$E$6+ U32*'Best Country'!$E$21+ W32*'Best Country'!$E$24+ Y32*'Best Country'!$E$27 )/SUM('Best Country'!$E$5:$E$28), "") -> 0.55290268 | J32: 0.5163944 | K32: =IFERROR(1-(J32-J$3)/(J$2-J$3), "") -> 0.29235474 | L32: 0.786 | M32: =IFERROR((L32-L$3)/(L$2-L$3), "") -> 0.68150685 | N32: 75.848 | O32: =IFERROR((N32-N$3)/(N$2-N$3), "") -> 0.68448342 | P32: 9990 | Q32: =IFERROR((P32-P$3)/(P$2-P$3), "") -> 0.037109015 | R32: 19.7 | S32: =IFERROR(1-(R32-R$3)/(R$2-R$3), "") -> 0.89879518 | T32: 35.8 | U32: =IFERROR((T32-T$3)/(T$2-T$3), "") -> 0.24809741 | V32: 59.2 | W32: =IFERROR(1-(V32-V$3)/(V$2-V$3), "") -> 0.58649789 | X32: 6.494 | Y32: =IFERROR((X32-X$3)/(X$2-X$3), "") -> 0.80508475
A33: Ratings by Continent: | D33: Iceland | E33: 72.73 | G33: North America | H33: British Virgin Islands | I33: =IFERROR(( K33*'Best Country'!$E$12+ M33*'Best Country'!$E$15+ O33*'Best Country'!$E$18+ Q33*'Best Country'!$E$9+ S33*'Best Country'!$E$6+ U33*'Best Country'!$E$21+ W33*'Best Country'!$E$24+ Y33*'Best Country'!$E$27 )/SUM('Best Country'!$E$5:$E$28), "") | K33: =IFERROR(1-(J33-J$3)/(J$2-J$3), "") | M33: =IFERROR((L33-L$3)/(L$2-L$3), "") | O33: =IFERROR((N33-N$3)/(N$2-N$3), "") | P33: 37900 | Q33: =IFERROR((P33-P$3)/(P$2-P$3), "") -> 0.14430345 | S33: =IFERROR(1-(R33-R$3)/(R$2-R$3), "") | U33: =IFERROR((T33-T$3)/(T$2-T$3), "") | W33: =IFERROR(1-(V33-V$3)/(V$2-V$3), "") | Y33: =IFERROR((X33-X$3)/(X$2-X$3), "")
A34: ='Best Country'!H3 -> Europe | D34: India | E34: 54.24 | G34: Asia | H34: Brunei | I34: =IFERROR(( K34*'Best Country'!$E$12+ M34*'Best Country'!$E$15+ O34*'Best Country'!$E$18+ Q34*'Best Country'!$E$9+ S34*'Best Country'!$E$6+ U34*'Best Country'!$E$21+ W34*'Best Country'!$E$24+ Y34*'Best Country'!$E$27 )/SUM('Best Country'!$E$5:$E$28), "") | K34: =IFERROR(1-(J34-J$3)/(J$2-J$3), "") | L34: 0.837 | M34: =IFERROR((L34-L$3)/(L$2-L$3), "") -> 0.76883562 | N34: 75.327 | O34: =IFERROR((N34-N$3)/(N$2-N$3), "") -> 0.66780822 | P34: 34325 | Q34: =IFERROR((P34-P$3)/(P$2-P$3), "") -> 0.13057288 | R34: 33.4 | S34: =IFERROR(1-(R34-R$3)/(R$2-R$3), "") -> 0.73373494 | U34: =IFERROR((T34-T$3)/(T$2-T$3), "") | W34: =IFERROR(1-(V34-V$3)/(V$2-V$3), "") | Y34: =IFERROR((X34-X$3)/(X$2-X$3), "")
A35: Country | B35: Rating | D35: Indonesia | E35: 56.05 | G35: Europe | H35: Bulgaria | I35: =IFERROR(( K35*'Best Country'!$E$12+ M35*'Best Country'!$E$15+ O35*'Best Country'!$E$18+ Q35*'Best Country'!$E$9+ S35*'Best Country'!$E$6+ U35*'Best Country'!$E$21+ W35*'Best Country'!$E$24+ Y35*'Best Country'!$E$27 )/SUM('Best Country'!$E$5:$E$28), "") -> 0.60840415 | J35: 0.38201502 | K35: =IFERROR(1-(J35-J$3)/(J$2-J$3), "") -> 0.63738797 | L35: 0.845 | M35: =IFERROR((L35-L$3)/(L$2-L$3), "") -> 0.78253425 | N35: 75.636 | O35: =IFERROR((N35-N$3)/(N$2-N$3), "") -> 0.67769812 | P35: 17426 | Q35: =IFERROR((P35-P$3)/(P$2-P$3), "") -> 0.065668592 | R35: 27.3 | S35: =IFERROR(1-(R35-R$3)/(R$2-R$3), "") -> 0.80722892 | T35: 64.1 | U35: =IFERROR((T35-T$3)/(T$2-T$3), "") -> 0.67884323 | V35: 58.2 | W35: =IFERROR(1-(V35-V$3)/(V$2-V$3), "") -> 0.60759494 | X35: 5.554 | Y35: =IFERROR((X35-X$3)/(X$2-X$3), "") -> 0.65756434
D36: Iran | E36: 59.21 | G36: Africa | H36: Burkina Faso | I36: =IFERROR(( K36*'Best Country'!$E$12+ M36*'Best Country'!$E$15+ O36*'Best Country'!$E$18+ Q36*'Best Country'!$E$9+ S36*'Best Country'!$E$6+ U36*'Best Country'!$E$21+ W36*'Best Country'!$E$24+ Y36*'Best Country'!$E$27 )/SUM('Best Country'!$E$5:$E$28), "") | J36: 0.37391287 | K36: =IFERROR(1-(J36-J$3)/(J$2-J$3), "") -> 0.6581911 | L36: 0.459 | M36: =IFERROR((L36-L$3)/(L$2-L$3), "") -> 0.12157534 | N36: 61.092 | O36: =IFERROR((N36-N$3)/(N$2-N$3), "") -> 0.21220074 | P36: 1124 | Q36: =IFERROR((P36-P$3)/(P$2-P$3), "") -> 0.0030572113 | S36: =IFERROR(1-(R36-R$3)/(R$2-R$3), "") | U36: =IFERROR((T36-T$3)/(T$2-T$3), "") | W36: =IFERROR(1-(V36-V$3)/(V$2-V$3), "") | X36: 4.383 | Y36: =IFERROR((X36-X$3)/(X$2-X$3), "") -> 0.47379159
A37: {=_xlfn._xlws.FILTER(_xlfn.ANCHORARRAY(H5), ((A34="World") + (A34=_xlfn.ANCHORARRAY(G5))) * (I5:I238<>""))} -> Albania | B37: {=ROUND(_xlfn._xlws.FILTER(I5:I238*100, ((A34="World") + (A34=_xlfn.ANCHORARRAY(G5))) * (I5:I238<>"")), B1)} -> 62.38 | D37: Ireland | E37: 72.6 | G37: Africa | H37: Burundi | I37: =IFERROR(( K37*'Best Country'!$E$12+ M37*'Best Country'!$E$15+ O37*'Best Country'!$E$18+ Q37*'Best Country'!$E$9+ S37*'Best Country'!$E$6+ U37*'Best Country'!$E$21+ W37*'Best Country'!$E$24+ Y37*'Best Country'!$E$27 )/SUM('Best Country'!$E$5:$E$28), "") | J37: 0.37456086 | K37: =IFERROR(1-(J37-J$3)/(J$2-J$3), "") -> 0.65652731 | L37: 0.439 | M37: =IFERROR((L37-L$3)/(L$2-L$3), "") -> 0.087328767 | N37: 63.651 | O37: =IFERROR((N37-N$3)/(N$2-N$3), "") -> 0.29410447 | P37: 469 | Q37: =IFERROR((P37-P$3)/(P$2-P$3), "") -> 0.0005415412 | S37: =IFERROR(1-(R37-R$3)/(R$2-R$3), "") | U37: =IFERROR((T37-T$3)/(T$2-T$3), "") | W37: =IFERROR(1-(V37-V$3)/(V$2-V$3), "") | Y37: =IFERROR((X37-X$3)/(X$2-X$3), "")
A38: Austria | B38: 68.5 | D38: Israel | E38: 67.67 | G38: Asia | H38: Cambodia | I38: =IFERROR(( K38*'Best Country'!$E$12+ M38*'Best Country'!$E$15+ O38*'Best Country'!$E$18+ Q38*'Best Country'!$E$9+ S38*'Best Country'!$E$6+ U38*'Best Country'!$E$21+ W38*'Best Country'!$E$24+ Y38*'Best Country'!$E$27 )/SUM('Best Country'!$E$5:$E$28), "") | K38: =IFERROR(1-(J38-J$3)/(J$2-J$3), "") | L38: 0.606 | M38: =IFERROR((L38-L$3)/(L$2-L$3), "") -> 0.37328767 | N38: 70.668 | O38: =IFERROR((N38-N$3)/(N$2-N$3), "") -> 0.51869159 | P38: 2790 | Q38: =IFERROR((P38-P$3)/(P$2-P$3), "") -> 0.0094558471 | R38: 22.6 | S38: =IFERROR(1-(R38-R$3)/(R$2-R$3), "") -> 0.86385542 | U38: =IFERROR((T38-T$3)/(T$2-T$3), "") | W38: =IFERROR(1-(V38-V$3)/(V$2-V$3), "") | X38: 4.341 | Y38: =IFERROR((X38-X$3)/(X$2-X$3), "") -> 0.46720025
A39: Belgium | B39: 68.78 | D39: Italy | E39: 66.32 | G39: Africa | H39: Cameroon | I39: =IFERROR(( K39*'Best Country'!$E$12+ M39*'Best Country'!$E$15+ O39*'Best Country'!$E$18+ Q39*'Best Country'!$E$9+ S39*'Best Country'!$E$6+ U39*'Best Country'!$E$21+ W39*'Best Country'!$E$24+ Y39*'Best Country'!$E$27 )/SUM('Best Country'!$E$5:$E$28), "") | J39: 0.42176074 | K39: =IFERROR(1-(J39-J$3)/(J$2-J$3), "") -> 0.53533664 | L39: 0.588 | M39: =IFERROR((L39-L$3)/(L$2-L$3), "") -> 0.34246575 | N39: 63.7 | O39: =IFERROR((N39-N$3)/(N$2-N$3), "") -> 0.29567277 | P39: 1875 | Q39: =IFERROR((P39-P$3)/(P$2-P$3), "") -> 0.0059415904 | R39: 30.5 | S39: =IFERROR(1-(R39-R$3)/(R$2-R$3), "") -> 0.7686747 | U39: =IFERROR((T39-T$3)/(T$2-T$3), "") | W39: =IFERROR(1-(V39-V$3)/(V$2-V$3), "") | X39: 4.887 | Y39: =IFERROR((X39-X$3)/(X$2-X$3), "") -> 0.55288763
A40: Bosnia and Herzegovina | B40: 63.45 | D40: Japan | E40: 68.26 | G40: North America | H40: Canada | I40: =IFERROR(( K40*'Best Country'!$E$12+ M40*'Best Country'!$E$15+ O40*'Best Country'!$E$18+ Q40*'Best Country'!$E$9+ S40*'Best Country'!$E$6+ U40*'Best Country'!$E$21+ W40*'Best Country'!$E$24+ Y40*'Best Country'!$E$27 )/SUM('Best Country'!$E$5:$E$28), "") -> 0.68289163 | J40: 0.29851684 | K40: =IFERROR(1-(J40-J$3)/(J$2-J$3), "") -> 0.85177835 | L40: 0.939 | M40: =IFERROR((L40-L$3)/(L$2-L$3), "") -> 0.94349315 | N40: 82.63 | O40: =IFERROR((N40-N$3)/(N$2-N$3), "") -> 0.9015491 | P40: 55458 | Q40: =IFERROR((P40-P$3)/(P$2-P$3), "") -> 0.21173877 | R40: 48.1 | S40: =IFERROR(1-(R40-R$3)/(R$2-R$3), "") -> 0.55662651 | T40: 54.2 | U40: =IFERROR((T40-T$3)/(T$2-T$3), "") -> 0.5281583 | V40: 68.6 | W40: =IFERROR(1-(V40-V$3)/(V$2-V$3), "") -> 0.38818565 | X40: 6.803 | Y40: =IFERROR((X40-X$3)/(X$2-X$3), "") -> 0.85357815
A41: Bulgaria | B41: 60.84 | D41: Jordan | E41: 54.7 | G41: Africa | H41: Cape Verde | I41: =IFERROR(( K41*'Best Country'!$E$12+ M41*'Best Country'!$E$15+ O41*'Best Country'!$E$18+ Q41*'Best Country'!$E$9+ S41*'Best Country'!$E$6+ U41*'Best Country'!$E$21+ W41*'Best Country'!$E$24+ Y41*'Best Country'!$E$27 )/SUM('Best Country'!$E$5:$E$28), "") | J41: 0.42381087 | K41: =IFERROR(1-(J41-J$3)/(J$2-J$3), "") -> 0.53007272 | L41: 0.668 | M41: =IFERROR((L41-L$3)/(L$2-L$3), "") -> 0.47945205 | N41: 76.059 | O41: =IFERROR((N41-N$3)/(N$2-N$3), "") -> 0.69123672 | P41: 5283 | Q41: =IFERROR((P41-P$3)/(P$2-P$3), "") -> 0.019030756 | S41: =IFERROR(1-(R41-R$3)/(R$2-R$3), "") | U41: =IFERROR((T41-T$3)/(T$2-T$3), "") | W41: =IFERROR(1-(V41-V$3)/(V$2-V$3), "") | Y41: =IFERROR((X41-X$3)/(X$2-X$3), "")
A42: Croatia | B42: 66.07 | D42: Kazakhstan | E42: 64.54 | G42: North America | H42: Cayman Islands | I42: =IFERROR(( K42*'Best Country'!$E$12+ M42*'Best Country'!$E$15+ O42*'Best Country'!$E$18+ Q42*'Best Country'!$E$9+ S42*'Best Country'!$E$6+ U42*'Best Country'!$E$21+ W42*'Best Country'!$E$24+ Y42*'Best Country'!$E$27 )/SUM('Best Country'!$E$5:$E$28), "") | K42: =IFERROR(1-(J42-J$3)/(J$2-J$3), "") | M42: =IFERROR((L42-L$3)/(L$2-L$3), "") | O42: =IFERROR((N42-N$3)/(N$2-N$3), "") | P42: 93972 | Q42: =IFERROR((P42-P$3)/(P$2-P$3), "") -> 0.35966017 | R42: 94.3 | S42: =IFERROR(1-(R42-R$3)/(R$2-R$3), "") -> 0 | U42: =IFERROR((T42-T$3)/(T$2-T$3), "") | W42: =IFERROR(1-(V42-V$3)/(V$2-V$3), "") | Y42: =IFERROR((X42-X$3)/(X$2-X$3), "")
A43: Cyprus | B43: 66.74 | D43: Kenya | E43: 44.36 | G43: Africa | H43: Central African Republic | I43: =IFERROR(( K43*'Best Country'!$E$12+ M43*'Best Country'!$E$15+ O43*'Best Country'!$E$18+ Q43*'Best Country'!$E$9+ S43*'Best Country'!$E$6+ U43*'Best Country'!$E$21+ W43*'Best Country'!$E$24+ Y43*'Best Country'!$E$27 )/SUM('Best Country'!$E$5:$E$28), "") | J43: 0.43034458 | K43: =IFERROR(1-(J43-J$3)/(J$2-J$3), "") -> 0.51329673 | L43: 0.414 | M43: =IFERROR((L43-L$3)/(L$2-L$3), "") -> 0.044520548 | N43: 57.408 | O43: =IFERROR((N43-N$3)/(N$2-N$3), "") -> 0.094290104 | P43: 532 | Q43: =IFERROR((P43-P$3)/(P$2-P$3), "") -> 0.00078350642 | S43: =IFERROR(1-(R43-R$3)/(R$2-R$3), "") | U43: =IFERROR((T43-T$3)/(T$2-T$3), "") | W43: =IFERROR(1-(V43-V$3)/(V$2-V$3), "") | Y43: =IFERROR((X43-X$3)/(X$2-X$3), "")
A44: Czech Republic | B44: 69.85 | D44: Latvia | E44: 64.36 | G44: Africa | H44: Chad | I44: =IFERROR(( K44*'Best Country'!$E$12+ M44*'Best Country'!$E$15+ O44*'Best Country'!$E$18+ Q44*'Best Country'!$E$9+ S44*'Best Country'!$E$6+ U44*'Best Country'!$E$21+ W44*'Best Country'!$E$24+ Y44*'Best Country'!$E$27 )/SUM('Best Country'!$E$5:$E$28), "") | J44: 0.37357685 | K44: =IFERROR(1-(J44-J$3)/(J$2-J$3), "") -> 0.65905386 | L44: 0.416 | M44: =IFERROR((L44-L$3)/(L$2-L$3), "") -> 0.047945205 | N44: 55.069 | O44: =IFERROR((N44-N$3)/(N$2-N$3), "") -> 0.01942773 | P44: 895 | Q44: =IFERROR((P44-P$3)/(P$2-P$3), "") -> 0.002177687 | S44: =IFERROR(1-(R44-R$3)/(R$2-R$3), "") | U44: =IFERROR((T44-T$3)/(T$2-T$3), "") | W44: =IFERROR(1-(V44-V$3)/(V$2-V$3), "") | X44: 4.384 | Y44: =IFERROR((X44-X$3)/(X$2-X$3), "") -> 0.47394852
A45: Denmark | B45: 72.46 | D45: Lebanon | E45: 49.44 | G45: South America | H45: Chile | I45: =IFERROR(( K45*'Best Country'!$E$12+ M45*'Best Country'!$E$15+ O45*'Best Country'!$E$18+ Q45*'Best Country'!$E$9+ S45*'Best Country'!$E$6+ U45*'Best Country'!$E$21+ W45*'Best Country'!$E$24+ Y45*'Best Country'!$E$27 )/SUM('Best Country'!$E$5:$E$28), "") -> 0.61192848 | J45: 0.43042782 | K45: =IFERROR(1-(J45-J$3)/(J$2-J$3), "") -> 0.513083 | L45: 0.878 | M45: =IFERROR((L45-L$3)/(L$2-L$3), "") -> 0.8390411 | N45: 81.167 | O45: =IFERROR((N45-N$3)/(N$2-N$3), "") -> 0.85472411 | P45: 17312 | Q45: =IFERROR((P45-P$3)/(P$2-P$3), "") -> 0.06523075 | R45: 25.1 | S45: =IFERROR(1-(R45-R$3)/(R$2-R$3), "") -> 0.83373494 | T45: 39.5 | U45: =IFERROR((T45-T$3)/(T$2-T$3), "") -> 0.304414 | V45: 63.7 | W45: =IFERROR(1-(V45-V$3)/(V$2-V$3), "") -> 0.49156118 | X45: 6.361 | Y45: =IFERROR((X45-X$3)/(X$2-X$3), "") -> 0.78421218
A46: Estonia | B46: 66.57 | D46: Lithuania | E46: 64.59 | G46: Asia | H46: China | I46: =IFERROR(( K46*'Best Country'!$E$12+ M46*'Best Country'!$E$15+ O46*'Best Country'!$E$18+ Q46*'Best Country'!$E$9+ S46*'Best Country'!$E$6+ U46*'Best Country'!$E$21+ W46*'Best Country'!$E$24+ Y46*'Best Country'!$E$27 )/SUM('Best Country'!$E$5:$E$28), "") -> 0.6291515 | J46: 0.35743752 | K46: =IFERROR(1-(J46-J$3)/(J$2-J$3), "") -> 0.70049329 | L46: 0.797 | M46: =IFERROR((L46-L$3)/(L$2-L$3), "") -> 0.70034247 | N46: 77.953 | O46: =IFERROR((N46-N$3)/(N$2-N$3), "") -> 0.75185636 | P46: 13581 | Q46: =IFERROR((P46-P$3)/(P$2-P$3), "") -> 0.050901032 | R46: 21.2 | S46: =IFERROR(1-(R46-R$3)/(R$2-R$3), "") -> 0.88072289 | T46: 76.5 | U46: =IFERROR((T46-T$3)/(T$2-T$3), "") -> 0.86757991 | V46: 68.7 | W46: =IFERROR(1-(V46-V$3)/(V$2-V$3), "") -> 0.38607595 | X46: 5.921 | Y46: =IFERROR((X46-X$3)/(X$2-X$3), "") -> 0.71516008
A47: Finland | B47: 73.26 | D47: Luxembourg | E47: 70.86 | G47: South America | H47: Colombia | I47: =IFERROR(( K47*'Best Country'!$E$12+ M47*'Best Country'!$E$15+ O47*'Best Country'!$E$18+ Q47*'Best Country'!$E$9+ S47*'Best Country'!$E$6+ U47*'Best Country'!$E$21+ W47*'Best Country'!$E$24+ Y47*'Best Country'!$E$27 )/SUM('Best Country'!$E$5:$E$28), "") -> 0.52866701 | J47: 0.53881925 | K47: =IFERROR(1-(J47-J$3)/(J$2-J$3), "") -> 0.23477658 | L47: 0.788 | M47: =IFERROR((L47-L$3)/(L$2-L$3), "") -> 0.68493151 | N47: 77.725 | O47: =IFERROR((N47-N$3)/(N$2-N$3), "") -> 0.74455896 | P47: 8007 | Q47: =IFERROR((P47-P$3)/(P$2-P$3), "") -> 0.029492872 | R47: 19.9 | S47: =IFERROR(1-(R47-R$3)/(R$2-R$3), "") -> 0.89638554 | T47: 39 | U47: =IFERROR((T47-T$3)/(T$2-T$3), "") -> 0.29680365 | V47: 68.9 | W47: =IFERROR(1-(V47-V$3)/(V$2-V$3), "") -> 0.38185654 | X47: 6.004 | Y47: =IFERROR((X47-X$3)/(X$2-X$3), "") -> 0.72818581
A48: France | B48: 64.44 | D48: Malaysia | E48: 58.24 | G48: Africa | H48: Comoros | I48: =IFERROR(( K48*'Best Country'!$E$12+ M48*'Best Country'!$E$15+ O48*'Best Country'!$E$18+ Q48*'Best Country'!$E$9+ S48*'Best Country'!$E$6+ U48*'Best Country'!$E$21+ W48*'Best Country'!$E$24+ Y48*'Best Country'!$E$27 )/SUM('Best Country'!$E$5:$E$28), "") | J48: 0.45332187 | K48: =IFERROR(1-(J48-J$3)/(J$2-J$3), "") -> 0.45430012 | L48: 0.603 | M48: =IFERROR((L48-L$3)/(L$2-L$3), "") -> 0.36815068 | N48: 66.777 | O48: =IFERROR((N48-N$3)/(N$2-N$3), "") -> 0.39415568 | P48: 1753 | Q48: =IFERROR((P48-P$3)/(P$2-P$3), "") -> 0.0054730228 | S48: =IFERROR(1-(R48-R$3)/(R$2-R$3), "") | U48: =IFERROR((T48-T$3)/(T$2-T$3), "") | W48: =IFERROR(1-(V48-V$3)/(V$2-V$3), "") | X48: 3.754 | Y48: =IFERROR((X48-X$3)/(X$2-X$3), "") -> 0.37507847
A49: Germany | B49: 68.11 | D49: Malta | E49: 68.33 | G49: Oceania | H49: Cook Islands | I49: =IFERROR(( K49*'Best Country'!$E$12+ M49*'Best Country'!$E$15+ O49*'Best Country'!$E$18+ Q49*'Best Country'!$E$9+ S49*'Best Country'!$E$6+ U49*'Best Country'!$E$21+ W49*'Best Country'!$E$24+ Y49*'Best Country'!$E$27 )/SUM('Best Country'!$E$5:$E$28), "") | K49: =IFERROR(1-(J49-J$3)/(J$2-J$3), "") | M49: =IFERROR((L49-L$3)/(L$2-L$3), "") | O49: =IFERROR((N49-N$3)/(N$2-N$3), "") | P49: 27612 | Q49: =IFERROR((P49-P$3)/(P$2-P$3), "") -> 0.10479014 | S49: =IFERROR(1-(R49-R$3)/(R$2-R$3), "") | U49: =IFERROR((T49-T$3)/(T$2-T$3), "") | W49: =IFERROR(1-(V49-V$3)/(V$2-V$3), "") | Y49: =IFERROR((X49-X$3)/(X$2-X$3), "")
A50: Greece | B50: 64.83 | D50: Mexico | E50: 57.3 | G50: North America | H50: Costa Rica | I50: =IFERROR(( K50*'Best Country'!$E$12+ M50*'Best Country'!$E$15+ O50*'Best Country'!$E$18+ Q50*'Best Country'!$E$9+ S50*'Best Country'!$E$6+ U50*'Best Country'!$E$21+ W50*'Best Country'!$E$24+ Y50*'Best Country'!$E$27 )/SUM('Best Country'!$E$5:$E$28), "") -> 0.6081071 | J50: 0.4582914 | K50: =IFERROR(1-(J50-J$3)/(J$2-J$3), "") -> 0.44154032 | L50: 0.833 | M50: =IFERROR((L50-L$3)/(L$2-L$3), "") -> 0.7619863 | N50: 80.799 | O50: =IFERROR((N50-N$3)/(N$2-N$3), "") -> 0.84294585 | P50: 19909 | Q50: =IFERROR((P50-P$3)/(P$2-P$3), "") -> 0.075205094 | R50: 36.6 | S50: =IFERROR(1-(R50-R$3)/(R$2-R$3), "") -> 0.69518072 | T50: 46.3 | U50: =IFERROR((T50-T$3)/(T$2-T$3), "") -> 0.40791476 | V50: 65.1 | W50: =IFERROR(1-(V50-V$3)/(V$2-V$3), "") -> 0.46202532 | X50: 7.274 | Y50: =IFERROR((X50-X$3)/(X$2-X$3), "") -> 0.92749529
A51: Hungary | B51: 66.17 | D51: Morocco | E51: 53.93 | G51: Europe | H51: Croatia | I51: =IFERROR(( K51*'Best Country'!$E$12+ M51*'Best Country'!$E$15+ O51*'Best Country'!$E$18+ Q51*'Best Country'!$E$9+ S51*'Best Country'!$E$6+ U51*'Best Country'!$E$21+ W51*'Best Country'!$E$24+ Y51*'Best Country'!$E$27 )/SUM('Best Country'!$E$5:$E$28), "") -> 0.66071541 | J51: 0.30017322 | K51: =IFERROR(1-(J51-J$3)/(J$2-J$3), "") -> 0.84752542 | L51: 0.889 | M51: =IFERROR((L51-L$3)/(L$2-L$3), "") -> 0.85787671 | N51: 78.58 | O51: =IFERROR((N51-N$3)/(N$2-N$3), "") -> 0.77192421 | P51: 25714 | Q51: =IFERROR((P51-P$3)/(P$2-P$3), "") -> 0.097500461 | R51: 35 | S51: =IFERROR(1-(R51-R$3)/(R$2-R$3), "") -> 0.71445783 | T51: 74.6 | U51: =IFERROR((T51-T$3)/(T$2-T$3), "") -> 0.83866058 | V51: 64.8 | W51: =IFERROR(1-(V51-V$3)/(V$2-V$3), "") -> 0.46835443 | X51: 5.87 | Y51: =IFERROR((X51-X$3)/(X$2-X$3), "") -> 0.70715631
A52: Iceland | B52: 72.73 | D52: Netherlands | E52: 71.98 | G52: North America | H52: Cuba | I52: =IFERROR(( K52*'Best Country'!$E$12+ M52*'Best Country'!$E$15+ O52*'Best Country'!$E$18+ Q52*'Best Country'!$E$9+ S52*'Best Country'!$E$6+ U52*'Best Country'!$E$21+ W52*'Best Country'!$E$24+ Y52*'Best Country'!$E$27 )/SUM('Best Country'!$E$5:$E$28), "") | K52: =IFERROR(1-(J52-J$3)/(J$2-J$3), "") | L52: 0.762 | M52: =IFERROR((L52-L$3)/(L$2-L$3), "") -> 0.64041096 | N52: 78.085 | O52: =IFERROR((N52-N$3)/(N$2-N$3), "") -> 0.75608117 | P52: 18468 | Q52: =IFERROR((P52-P$3)/(P$2-P$3), "") -> 0.06967062 | R52: 27.8 | S52: =IFERROR(1-(R52-R$3)/(R$2-R$3), "") -> 0.80120482 | U52: =IFERROR((T52-T$3)/(T$2-T$3), "") | W52: =IFERROR(1-(V52-V$3)/(V$2-V$3), "") | Y52: =IFERROR((X52-X$3)/(X$2-X$3), "")
A53: Ireland | B53: 72.6 | D53: Nigeria | E53: 40.88 | G53: North America | H53: Curacao | I53: =IFERROR(( K53*'Best Country'!$E$12+ M53*'Best Country'!$E$15+ O53*'Best Country'!$E$18+ Q53*'Best Country'!$E$9+ S53*'Best Country'!$E$6+ U53*'Best Country'!$E$21+ W53*'Best Country'!$E$24+ Y53*'Best Country'!$E$27 )/SUM('Best Country'!$E$5:$E$28), "") | K53: =IFERROR(1-(J53-J$3)/(J$2-J$3), "") | M53: =IFERROR((L53-L$3)/(L$2-L$3), "") | O53: =IFERROR((N53-N$3)/(N$2-N$3), "") | P53: 17691 | Q53: =IFERROR((P53-P$3)/(P$2-P$3), "") -> 0.066686382 | S53: =IFERROR(1-(R53-R$3)/(R$2-R$3), "") | U53: =IFERROR((T53-T$3)/(T$2-T$3), "") | W53: =IFERROR(1-(V53-V$3)/(V$2-V$3), "") | Y53: =IFERROR((X53-X$3)/(X$2-X$3), "")
A54: Italy | B54: 66.32 | D54: North Macedonia | E54: 61.69 | G54: Europe | H54: Cyprus | I54: =IFERROR(( K54*'Best Country'!$E$12+ M54*'Best Country'!$E$15+ O54*'Best Country'!$E$18+ Q54*'Best Country'!$E$9+ S54*'Best Country'!$E$6+ U54*'Best Country'!$E$21+ W54*'Best Country'!$E$24+ Y54*'Best Country'!$E$27 )/SUM('Best Country'!$E$5:$E$28), "") -> 0.66735699 | J54: 0.31534076 | K54: =IFERROR(1-(J54-J$3)/(J$2-J$3), "") -> 0.80858116 | L54: 0.913 | M54: =IFERROR((L54-L$3)/(L$2-L$3), "") -> 0.8989726 | N54: 81.648 | O54: =IFERROR((N54-N$3)/(N$2-N$3), "") -> 0.87011906 | P54: 28259 | Q54: =IFERROR((P54-P$3)/(P$2-P$3), "") -> 0.10727509 | R54: 42.8 | S54: =IFERROR(1-(R54-R$3)/(R$2-R$3), "") -> 0.62048193 | T54: 67.3 | U54: =IFERROR((T54-T$3)/(T$2-T$3), "") -> 0.72754947 | V54: 56.5 | W54: =IFERROR(1-(V54-V$3)/(V$2-V$3), "") -> 0.64345992 | X54: 5.942 | Y54: =IFERROR((X54-X$3)/(X$2-X$3), "") -> 0.71845574
A55: Latvia | B55: 64.36 | D55: Norway | E55: 72.93 | G55: Europe | H55: Czech Republic | I55: =IFERROR(( K55*'Best Country'!$E$12+ M55*'Best Country'!$E$15+ O55*'Best Country'!$E$18+ Q55*'Best Country'!$E$9+ S55*'Best Country'!$E$6+ U55*'Best Country'!$E$21+ W55*'Best Country'!$E$24+ Y55*'Best Country'!$E$27 )/SUM('Best Country'!$E$5:$E$28), "") -> 0.69845429 | J55: 0.2587039 | K55: =IFERROR(1-(J55-J$3)/(J$2-J$3), "") -> 0.95400227 | L55: 0.915 | M55: =IFERROR((L55-L$3)/(L$2-L$3), "") -> 0.90239726 | N55: 79.834 | O55: =IFERROR((N55-N$3)/(N$2-N$3), "") -> 0.81205992 | P55: 33956 | Q55: =IFERROR((P55-P$3)/(P$2-P$3), "") -> 0.12915566 | R55: 35.9 | S55: =IFERROR(1-(R55-R$3)/(R$2-R$3), "") -> 0.70361446 | T55: 73.4 | U55: =IFERROR((T55-T$3)/(T$2-T$3), "") -> 0.82039574 | V55: 75.5 | W55: =IFERROR(1-(V55-V$3)/(V$2-V$3), "") -> 0.24261603 | X55: 6.775 | Y55: =IFERROR((X55-X$3)/(X$2-X$3), "") -> 0.84918393
A56: Lithuania | B56: 64.59 | D56: Pakistan | E56: 49.87 | G56: Africa | H56: DR Congo | I56: =IFERROR(( K56*'Best Country'!$E$12+ M56*'Best Country'!$E$15+ O56*'Best Country'!$E$18+ Q56*'Best Country'!$E$9+ S56*'Best Country'!$E$6+ U56*'Best Country'!$E$21+ W56*'Best Country'!$E$24+ Y56*'Best Country'!$E$27 )/SUM('Best Country'!$E$5:$E$28), "") | J56: 0.4467324 | K56: =IFERROR(1-(J56-J$3)/(J$2-J$3), "") -> 0.47121927 | L56: 0.522 | M56: =IFERROR((L56-L$3)/(L$2-L$3), "") -> 0.22945205 | N56: 61.895 | O56: =IFERROR((N56-N$3)/(N$2-N$3), "") -> 0.23790168 | P56: 701 | Q56: =IFERROR((P56-P$3)/(P$2-P$3), "") -> 0.0014325877 | R56: 37.9 | S56: =IFERROR(1-(R56-R$3)/(R$2-R$3), "") -> 0.67951807 | U56: =IFERROR((T56-T$3)/(T$2-T$3), "") | W56: =IFERROR(1-(V56-V$3)/(V$2-V$3), "") | X56: 3.469 | Y56: =IFERROR((X56-X$3)/(X$2-X$3), "") -> 0.33035154
A57: Luxembourg | B57: 70.86 | D57: Panama | E57: 59.4 | G57: Europe | H57: Denmark | I57: =IFERROR(( K57*'Best Country'!$E$12+ M57*'Best Country'!$E$15+ O57*'Best Country'!$E$18+ Q57*'Best Country'!$E$9+ S57*'Best Country'!$E$6+ U57*'Best Country'!$E$21+ W57*'Best Country'!$E$24+ Y57*'Best Country'!$E$27 )/SUM('Best Country'!$E$5:$E$28), "") -> 0.72462218 | J57: 0.29259402 | K57: =IFERROR(1-(J57-J$3)/(J$2-J$3), "") -> 0.86698582 | L57: 0.962 | M57: =IFERROR((L57-L$3)/(L$2-L$3), "") -> 0.98287671 | N57: 81.933 | O57: =IFERROR((N57-N$3)/(N$2-N$3), "") -> 0.87924081 | P57: 74959 | Q57: =IFERROR((P57-P$3)/(P$2-P$3), "") -> 0.28663661 | R57: 54.3 | S57: =IFERROR(1-(R57-R$3)/(R$2-R$3), "") -> 0.48192771 | T57: 74 | U57: =IFERROR((T57-T$3)/(T$2-T$3), "") -> 0.82952816 | V57: 78.3 | W57: =IFERROR(1-(V57-V$3)/(V$2-V$3), "") -> 0.1835443 | X57: 7.521 | Y57: =IFERROR((X57-X$3)/(X$2-X$3), "") -> 0.96625863
A58: Malta | B58: 68.33 | D58: Peru | E58: 57.21 | G58: Africa | H58: Djibouti | I58: =IFERROR(( K58*'Best Country'!$E$12+ M58*'Best Country'!$E$15+ O58*'Best Country'!$E$18+ Q58*'Best Country'!$E$9+ S58*'Best Country'!$E$6+ U58*'Best Country'!$E$21+ W58*'Best Country'!$E$24+ Y58*'Best Country'!$E$27 )/SUM('Best Country'!$E$5:$E$28), "") | J58: 0.41586015 | K58: =IFERROR(1-(J58-J$3)/(J$2-J$3), "") -> 0.55048703 | L58: 0.513 | M58: =IFERROR((L58-L$3)/(L$2-L$3), "") -> 0.2140411 | N58: 65.987 | O58: =IFERROR((N58-N$3)/(N$2-N$3), "") -> 0.36887082 | P58: 3874 | Q58: =IFERROR((P58-P$3)/(P$2-P$3), "") -> 0.013619185 | S58: =IFERROR(1-(R58-R$3)/(R$2-R$3), "") | U58: =IFERROR((T58-T$3)/(T$2-T$3), "") | W58: =IFERROR(1-(V58-V$3)/(V$2-V$3), "") | Y58: =IFERROR((X58-X$3)/(X$2-X$3), "")
A59: Netherlands | B59: 71.98 | D59: Philippines | E59: 55.97 | G59: North America | H59: Dominica | I59: =IFERROR(( K59*'Best Country'!$E$12+ M59*'Best Country'!$E$15+ O59*'Best Country'!$E$18+ Q59*'Best Country'!$E$9+ S59*'Best Country'!$E$6+ U59*'Best Country'!$E$21+ W59*'Best Country'!$E$24+ Y59*'Best Country'!$E$27 )/SUM('Best Country'!$E$5:$E$28), "") | K59: =IFERROR(1-(J59-J$3)/(J$2-J$3), "") | L59: 0.761 | M59: =IFERROR((L59-L$3)/(L$2-L$3), "") -> 0.63869863 | N59: 71.132 | O59: =IFERROR((N59-N$3)/(N$2-N$3), "") -> 0.53354244 | P59: 11264 | Q59: =IFERROR((P59-P$3)/(P$2-P$3), "") -> 0.042002089 | S59: =IFERROR(1-(R59-R$3)/(R$2-R$3), "") | U59: =IFERROR((T59-T$3)/(T$2-T$3), "") | W59: =IFERROR(1-(V59-V$3)/(V$2-V$3), "") | Y59: =IFERROR((X59-X$3)/(X$2-X$3), "")
A60: North Macedonia | B60: 61.69 | D60: Poland | E60: 70.16 | G60: North America | H60: Dominican Republic | I60: =IFERROR(( K60*'Best Country'!$E$12+ M60*'Best Country'!$E$15+ O60*'Best Country'!$E$18+ Q60*'Best Country'!$E$9+ S60*'Best Country'!$E$6+ U60*'Best Country'!$E$21+ W60*'Best Country'!$E$24+ Y60*'Best Country'!$E$27 )/SUM('Best Country'!$E$5:$E$28), "") | J60: 0.38397565 | K60: =IFERROR(1-(J60-J$3)/(J$2-J$3), "") -> 0.63235385 | L60: 0.776 | M60: =IFERROR((L60-L$3)/(L$2-L$3), "") -> 0.66438356 | N60: 73.72 | O60: =IFERROR((N60-N$3)/(N$2-N$3), "") -> 0.61637434 | P60: 11096 | Q60: =IFERROR((P60-P$3)/(P$2-P$3), "") -> 0.041356849 | R60: 24 | S60: =IFERROR(1-(R60-R$3)/(R$2-R$3), "") -> 0.84698795 | U60: =IFERROR((T60-T$3)/(T$2-T$3), "") | W60: =IFERROR(1-(V60-V$3)/(V$2-V$3), "") | X60: 5.846 | Y60: =IFERROR((X60-X$3)/(X$2-X$3), "") -> 0.70338983
A61: Norway | B61: 72.93 | D61: Portugal | E61: 64.26 | G61: South America | H61: Ecuador | I61: =IFERROR(( K61*'Best Country'!$E$12+ M61*'Best Country'!$E$15+ O61*'Best Country'!$E$18+ Q61*'Best Country'!$E$9+ S61*'Best Country'!$E$6+ U61*'Best Country'!$E$21+ W61*'Best Country'!$E$24+ Y61*'Best Country'!$E$27 )/SUM('Best Country'!$E$5:$E$28), "") -> 0.5332802 | J61: 0.44579554 | K61: =IFERROR(1-(J61-J$3)/(J$2-J$3), "") -> 0.47362476 | L61: 0.777 | M61: =IFERROR((L61-L$3)/(L$2-L$3), "") -> 0.66609589 | N61: 77.392 | O61: =IFERROR((N61-N$3)/(N$2-N$3), "") -> 0.73390091 | P61: 6871 | Q61: =IFERROR((P61-P$3)/(P$2-P$3), "") -> 0.025129816 | R61: 20.1 | S61: =IFERROR(1-(R61-R$3)/(R$2-R$3), "") -> 0.8939759 | T61: 37.4 | U61: =IFERROR((T61-T$3)/(T$2-T$3), "") -> 0.27245053 | V61: 78 | W61: =IFERROR(1-(V61-V$3)/(V$2-V$3), "") -> 0.18987342 | X61: 5.965 | Y61: =IFERROR((X61-X$3)/(X$2-X$3), "") -> 0.72206529
A62: Poland | B62: 70.16 | D62: Romania | E62: 66.53 | G62: Africa | H62: Egypt | I62: =IFERROR(( K62*'Best Country'!$E$12+ M62*'Best Country'!$E$15+ O62*'Best Country'!$E$18+ Q62*'Best Country'!$E$9+ S62*'Best Country'!$E$6+ U62*'Best Country'!$E$21+ W62*'Best Country'!$E$24+ Y62*'Best Country'!$E$27 )/SUM('Best Country'!$E$5:$E$28), "") -> 0.5567722 | J62: 0.28482038 | K62: =IFERROR(1-(J62-J$3)/(J$2-J$3), "") -> 0.88694546 | L62: 0.754 | M62: =IFERROR((L62-L$3)/(L$2-L$3), "") -> 0.62671233 | N62: 71.633 | O62: =IFERROR((N62-N$3)/(N$2-N$3), "") -> 0.54957752 | P62: 2934 | Q62: =IFERROR((P62-P$3)/(P$2-P$3), "") -> 0.01000891 | R62: 12.8 | S62: =IFERROR(1-(R62-R$3)/(R$2-R$3), "") -> 0.98192771 | T62: 53.1 | U62: =IFERROR((T62-T$3)/(T$2-T$3), "") -> 0.51141553 | V62: 47.5 | W62: =IFERROR(1-(V62-V$3)/(V$2-V$3), "") -> 0.83333333 | X62: 3.817 | Y62: =IFERROR((X62-X$3)/(X$2-X$3), "") -> 0.38496547
A63: Portugal | B63: 64.26 | D63: Russia | E63: 60.53 | G63: North America | H63: El Salvador | I63: =IFERROR(( K63*'Best Country'!$E$12+ M63*'Best Country'!$E$15+ O63*'Best Country'!$E$18+ Q63*'Best Country'!$E$9+ S63*'Best Country'!$E$6+ U63*'Best Country'!$E$21+ W63*'Best Country'!$E$24+ Y63*'Best Country'!$E$27 )/SUM('Best Country'!$E$5:$E$28), "") | J63: 0.39802378 | K63: =IFERROR(1-(J63-J$3)/(J$2-J$3), "") -> 0.59628379 | L63: 0.678 | M63: =IFERROR((L63-L$3)/(L$2-L$3), "") -> 0.49657534 | N63: 72.099 | O63: =IFERROR((N63-N$3)/(N$2-N$3), "") -> 0.56449238 | P63: 5773 | Q63: =IFERROR((P63-P$3)/(P$2-P$3), "") -> 0.020912708 | R63: 28.2 | S63: =IFERROR(1-(R63-R$3)/(R$2-R$3), "") -> 0.79638554 | U63: =IFERROR((T63-T$3)/(T$2-T$3), "") | W63: =IFERROR(1-(V63-V$3)/(V$2-V$3), "") | X63: 6.492 | Y63: =IFERROR((X63-X$3)/(X$2-X$3), "") -> 0.80477087
A64: Romania | B64: 66.53 | D64: Serbia | E64: 65.66 | G64: Africa | H64: Equatorial Guinea | I64: =IFERROR(( K64*'Best Country'!$E$12+ M64*'Best Country'!$E$15+ O64*'Best Country'!$E$18+ Q64*'Best Country'!$E$9+ S64*'Best Country'!$E$6+ U64*'Best Country'!$E$21+ W64*'Best Country'!$E$24+ Y64*'Best Country'!$E$27 )/SUM('Best Country'!$E$5:$E$28), "") | J64: 0.38542363 | K64: =IFERROR(1-(J64-J$3)/(J$2-J$3), "") -> 0.62863601 | L64: 0.674 | M64: =IFERROR((L64-L$3)/(L$2-L$3), "") -> 0.48972603 | N64: 63.707 | O64: =IFERROR((N64-N$3)/(N$2-N$3), "") -> 0.29589681 | P64: 6543 | Q64: =IFERROR((P64-P$3)/(P$2-P$3), "") -> 0.023870061 | S64: =IFERROR(1-(R64-R$3)/(R$2-R$3), "") | U64: =IFERROR((T64-T$3)/(T$2-T$3), "") | W64: =IFERROR(1-(V64-V$3)/(V$2-V$3), "") | Y64: =IFERROR((X64-X$3)/(X$2-X$3), "")
A65: Serbia | B65: 65.66 | D65: Slovakia | E65: 68.89 | G65: Africa | H65: Eritrea | I65: =IFERROR(( K65*'Best Country'!$E$12+ M65*'Best Country'!$E$15+ O65*'Best Country'!$E$18+ Q65*'Best Country'!$E$9+ S65*'Best Country'!$E$6+ U65*'Best Country'!$E$21+ W65*'Best Country'!$E$24+ Y65*'Best Country'!$E$27 )/SUM('Best Country'!$E$5:$E$28), "") | K65: =IFERROR(1-(J65-J$3)/(J$2-J$3), "") | L65: 0.503 | M65: =IFERROR((L65-L$3)/(L$2-L$3), "") -> 0.19691781 | N65: 68.624 | O65: =IFERROR((N65-N$3)/(N$2-N$3), "") -> 0.45327103 | P65: 631 | Q65: =IFERROR((P65-P$3)/(P$2-P$3), "") -> 0.0011637375 | S65: =IFERROR(1-(R65-R$3)/(R$2-R$3), "") | U65: =IFERROR((T65-T$3)/(T$2-T$3), "") | W65: =IFERROR(1-(V65-V$3)/(V$2-V$3), "") | Y65: =IFERROR((X65-X$3)/(X$2-X$3), "")
A66: Slovakia | B66: 68.89 | D66: Slovenia | E66: 72.75 | G66: Europe | H66: Estonia | I66: =IFERROR(( K66*'Best Country'!$E$12+ M66*'Best Country'!$E$15+ O66*'Best Country'!$E$18+ Q66*'Best Country'!$E$9+ S66*'Best Country'!$E$6+ U66*'Best Country'!$E$21+ W66*'Best Country'!$E$24+ Y66*'Best Country'!$E$27 )/SUM('Best Country'!$E$5:$E$28), "") -> 0.66571648 | J66: 0.32252404 | K66: =IFERROR(1-(J66-J$3)/(J$2-J$3), "") -> 0.79013733 | L66: 0.905 | M66: =IFERROR((L66-L$3)/(L$2-L$3), "") -> 0.88527397 | N66: 79.153 | O66: =IFERROR((N66-N$3)/(N$2-N$3), "") -> 0.79026373 | P66: 33479 | Q66: =IFERROR((P66-P$3)/(P$2-P$3), "") -> 0.12732363 | R66: 38.5 | S66: =IFERROR(1-(R66-R$3)/(R$2-R$3), "") -> 0.67228916 | T66: 76.5 | U66: =IFERROR((T66-T$3)/(T$2-T$3), "") -> 0.86757991 | V66: 74.8 | W66: =IFERROR(1-(V66-V$3)/(V$2-V$3), "") -> 0.25738397 | X66: 6.417 | Y66: =IFERROR((X66-X$3)/(X$2-X$3), "") -> 0.79300063
A67: Slovenia | B67: 72.75 | D67: South Africa | E67: 40.96 | G67: Africa | H67: Eswatini | I67: =IFERROR(( K67*'Best Country'!$E$12+ M67*'Best Country'!$E$15+ O67*'Best Country'!$E$18+ Q67*'Best Country'!$E$9+ S67*'Best Country'!$E$6+ U67*'Best Country'!$E$21+ W67*'Best Country'!$E$24+ Y67*'Best Country'!$E$27 )/SUM('Best Country'!$E$5:$E$28), "") | J67: 0.54579794 | K67: =IFERROR(1-(J67-J$3)/(J$2-J$3), "") -> 0.21685806 | L67: 0.695 | M67: =IFERROR((L67-L$3)/(L$2-L$3), "") -> 0.52568493 | N67: 64.123 | O67: =IFERROR((N67-N$3)/(N$2-N$3), "") -> 0.30921137 | P67: 4365 | Q67: =IFERROR((P67-P$3)/(P$2-P$3), "") -> 0.015504978 | S67: =IFERROR(1-(R67-R$3)/(R$2-R$3), "") | U67: =IFERROR((T67-T$3)/(T$2-T$3), "") | W67: =IFERROR(1-(V67-V$3)/(V$2-V$3), "") | X67: 3.774 | Y67: =IFERROR((X67-X$3)/(X$2-X$3), "") -> 0.3782172
A68: Spain | B68: 66.52 | D68: South Korea | E68: 65.82 | G68: Africa | H68: Ethiopia | I68: =IFERROR(( K68*'Best Country'!$E$12+ M68*'Best Country'!$E$15+ O68*'Best Country'!$E$18+ Q68*'Best Country'!$E$9+ S68*'Best Country'!$E$6+ U68*'Best Country'!$E$21+ W68*'Best Country'!$E$24+ Y68*'Best Country'!$E$27 )/SUM('Best Country'!$E$5:$E$28), "") | J68: 0.31141794 | K68: =IFERROR(1-(J68-J$3)/(J$2-J$3), "") -> 0.81865342 | L68: 0.497 | M68: =IFERROR((L68-L$3)/(L$2-L$3), "") -> 0.18664384 | N68: 67.315 | O68: =IFERROR((N68-N$3)/(N$2-N$3), "") -> 0.41137498 | P68: 867 | Q68: =IFERROR((P68-P$3)/(P$2-P$3), "") -> 0.0020701469 | R68: 30.7 | S68: =IFERROR(1-(R68-R$3)/(R$2-R$3), "") -> 0.76626506 | U68: =IFERROR((T68-T$3)/(T$2-T$3), "") | W68: =IFERROR(1-(V68-V$3)/(V$2-V$3), "") | X68: 3.898 | Y68: =IFERROR((X68-X$3)/(X$2-X$3), "") -> 0.39767734
A69: Sweden | B69: 70.59 | D69: Spain | E69: 66.52 | G69: South America | H69: Falkland Islands | I69: =IFERROR(( K69*'Best Country'!$E$12+ M69*'Best Country'!$E$15+ O69*'Best Country'!$E$18+ Q69*'Best Country'!$E$9+ S69*'Best Country'!$E$6+ U69*'Best Country'!$E$21+ W69*'Best Country'!$E$24+ Y69*'Best Country'!$E$27 )/SUM('Best Country'!$E$5:$E$28), "") | K69: =IFERROR(1-(J69-J$3)/(J$2-J$3), "") | M69: =IFERROR((L69-L$3)/(L$2-L$3), "") | O69: =IFERROR((N69-N$3)/(N$2-N$3), "") | Q69: =IFERROR((P69-P$3)/(P$2-P$3), "") | S69: =IFERROR(1-(R69-R$3)/(R$2-R$3), "") | U69: =IFERROR((T69-T$3)/(T$2-T$3), "") | W69: =IFERROR(1-(V69-V$3)/(V$2-V$3), "") | Y69: =IFERROR((X69-X$3)/(X$2-X$3), "")
A70: Switzerland | B70: 68.74 | D70: Sri Lanka | E70: 52.17 | G70: Europe | H70: Faroe Islands | I70: =IFERROR(( K70*'Best Country'!$E$12+ M70*'Best Country'!$E$15+ O70*'Best Country'!$E$18+ Q70*'Best Country'!$E$9+ S70*'Best Country'!$E$6+ U70*'Best Country'!$E$21+ W70*'Best Country'!$E$24+ Y70*'Best Country'!$E$27 )/SUM('Best Country'!$E$5:$E$28), "") | K70: =IFERROR(1-(J70-J$3)/(J$2-J$3), "") | M70: =IFERROR((L70-L$3)/(L$2-L$3), "") | O70: =IFERROR((N70-N$3)/(N$2-N$3), "") | Q70: =IFERROR((P70-P$3)/(P$2-P$3), "") | S70: =IFERROR(1-(R70-R$3)/(R$2-R$3), "") | U70: =IFERROR((T70-T$3)/(T$2-T$3), "") | W70: =IFERROR(1-(V70-V$3)/(V$2-V$3), "") | Y70: =IFERROR((X70-X$3)/(X$2-X$3), "")
A71: Ukraine | B71: 58.56 | D71: Sweden | E71: 70.59 | G71: Oceania | H71: Fiji | I71: =IFERROR(( K71*'Best Country'!$E$12+ M71*'Best Country'!$E$15+ O71*'Best Country'!$E$18+ Q71*'Best Country'!$E$9+ S71*'Best Country'!$E$6+ U71*'Best Country'!$E$21+ W71*'Best Country'!$E$24+ Y71*'Best Country'!$E$27 )/SUM('Best Country'!$E$5:$E$28), "") | J71: 0.30706868 | K71: =IFERROR(1-(J71-J$3)/(J$2-J$3), "") -> 0.8298206 | L71: 0.731 | M71: =IFERROR((L71-L$3)/(L$2-L$3), "") -> 0.58732877 | N71: 67.316 | O71: =IFERROR((N71-N$3)/(N$2-N$3), "") -> 0.41140699 | P71: 6705 | Q71: =IFERROR((P71-P$3)/(P$2-P$3), "") -> 0.024492257 | R71: 26.2 | S71: =IFERROR(1-(R71-R$3)/(R$2-R$3), "") -> 0.82048193 | U71: =IFERROR((T71-T$3)/(T$2-T$3), "") | W71: =IFERROR(1-(V71-V$3)/(V$2-V$3), "") | Y71: =IFERROR((X71-X$3)/(X$2-X$3), "")
A72: United Kingdom | B72: 65.85 | D72: Switzerland | E72: 68.74 | G72: Europe | H72: Finland | I72: =IFERROR(( K72*'Best Country'!$E$12+ M72*'Best Country'!$E$15+ O72*'Best Country'!$E$18+ Q72*'Best Country'!$E$9+ S72*'Best Country'!$E$6+ U72*'Best Country'!$E$21+ W72*'Best Country'!$E$24+ Y72*'Best Country'!$E$27 )/SUM('Best Country'!$E$5:$E$28), "") -> 0.73255255 | J72: 0.27925923 | K72: =IFERROR(1-(J72-J$3)/(J$2-J$3), "") -> 0.9012243 | L72: 0.948 | M72: =IFERROR((L72-L$3)/(L$2-L$3), "") -> 0.95890411 | N72: 81.91 | O72: =IFERROR((N72-N$3)/(N$2-N$3), "") -> 0.87850467 | P72: 54051 | Q72: =IFERROR((P72-P$3)/(P$2-P$3), "") -> 0.20633488 | R72: 45.6 | S72: =IFERROR(1-(R72-R$3)/(R$2-R$3), "") -> 0.58674699 | T72: 73.5 | U72: =IFERROR((T72-T$3)/(T$2-T$3), "") -> 0.82191781 | V72: 77.4 | W72: =IFERROR(1-(V72-V$3)/(V$2-V$3), "") -> 0.20253165 | X72: 7.736 | Y72: =IFERROR((X72-X$3)/(X$2-X$3), "") -> 1
D73: Thailand | E73: 60.04 | G73: Europe | H73: France | I73: =IFERROR(( K73*'Best Country'!$E$12+ M73*'Best Country'!$E$15+ O73*'Best Country'!$E$18+ Q73*'Best Country'!$E$9+ S73*'Best Country'!$E$6+ U73*'Best Country'!$E$21+ W73*'Best Country'!$E$24+ Y73*'Best Country'!$E$27 )/SUM('Best Country'!$E$5:$E$28), "") -> 0.6444174 | J73: 0.3123691 | K73: =IFERROR(1-(J73-J$3)/(J$2-J$3), "") -> 0.81621121 | L73: 0.92 | M73: =IFERROR((L73-L$3)/(L$2-L$3), "") -> 0.9109589 | N73: 83.325 | O73: =IFERROR((N73-N$3)/(N$2-N$3), "") -> 0.92379337 | P73: 48181 | Q73: =IFERROR((P73-P$3)/(P$2-P$3), "") -> 0.18378987 | R73: 46 | S73: =IFERROR(1-(R73-R$3)/(R$2-R$3), "") -> 0.58192771 | T73: 44.4 | U73: =IFERROR((T73-T$3)/(T$2-T$3), "") -> 0.37899543 | V73: 77.2 | W73: =IFERROR(1-(V73-V$3)/(V$2-V$3), "") -> 0.20675105 | X73: 6.593 | Y73: =IFERROR((X73-X$3)/(X$2-X$3), "") -> 0.82062147
D74: Tunisia | E74: 56.15 | G74: South America | H74: French Guiana | I74: =IFERROR(( K74*'Best Country'!$E$12+ M74*'Best Country'!$E$15+ O74*'Best Country'!$E$18+ Q74*'Best Country'!$E$9+ S74*'Best Country'!$E$6+ U74*'Best Country'!$E$21+ W74*'Best Country'!$E$24+ Y74*'Best Country'!$E$27 )/SUM('Best Country'!$E$5:$E$28), "") | K74: =IFERROR(1-(J74-J$3)/(J$2-J$3), "") | M74: =IFERROR((L74-L$3)/(L$2-L$3), "") | O74: =IFERROR((N74-N$3)/(N$2-N$3), "") | Q74: =IFERROR((P74-P$3)/(P$2-P$3), "") | S74: =IFERROR(1-(R74-R$3)/(R$2-R$3), "") | U74: =IFERROR((T74-T$3)/(T$2-T$3), "") | W74: =IFERROR(1-(V74-V$3)/(V$2-V$3), "") | Y74: =IFERROR((X74-X$3)/(X$2-X$3), "")
D75: Turkey | E75: 56.37 | G75: Oceania | H75: French Polynesia | I75: =IFERROR(( K75*'Best Country'!$E$12+ M75*'Best Country'!$E$15+ O75*'Best Country'!$E$18+ Q75*'Best Country'!$E$9+ S75*'Best Country'!$E$6+ U75*'Best Country'!$E$21+ W75*'Best Country'!$E$24+ Y75*'Best Country'!$E$27 )/SUM('Best Country'!$E$5:$E$28), "") | K75: =IFERROR(1-(J75-J$3)/(J$2-J$3), "") | M75: =IFERROR((L75-L$3)/(L$2-L$3), "") | O75: =IFERROR((N75-N$3)/(N$2-N$3), "") | P75: 22651 | Q75: =IFERROR((P75-P$3)/(P$2-P$3), "") -> 0.085736342 | S75: =IFERROR(1-(R75-R$3)/(R$2-R$3), "") | U75: =IFERROR((T75-T$3)/(T$2-T$3), "") | W75: =IFERROR(1-(V75-V$3)/(V$2-V$3), "") | Y75: =IFERROR((X75-X$3)/(X$2-X$3), "")
D76: Ukraine | E76: 58.56 | G76: Africa | H76: Gabon | I76: =IFERROR(( K76*'Best Country'!$E$12+ M76*'Best Country'!$E$15+ O76*'Best Country'!$E$18+ Q76*'Best Country'!$E$9+ S76*'Best Country'!$E$6+ U76*'Best Country'!$E$21+ W76*'Best Country'!$E$24+ Y76*'Best Country'!$E$27 )/SUM('Best Country'!$E$5:$E$28), "") | J76: 0.38024372 | K76: =IFERROR(1-(J76-J$3)/(J$2-J$3), "") -> 0.64193597 | L76: 0.733 | M76: =IFERROR((L76-L$3)/(L$2-L$3), "") -> 0.59075342 | N76: 68.337 | O76: =IFERROR((N76-N$3)/(N$2-N$3), "") -> 0.44408526 | P76: 7863 | Q76: =IFERROR((P76-P$3)/(P$2-P$3), "") -> 0.028939808 | S76: =IFERROR(1-(R76-R$3)/(R$2-R$3), "") | U76: =IFERROR((T76-T$3)/(T$2-T$3), "") | W76: =IFERROR(1-(V76-V$3)/(V$2-V$3), "") | X76: 5.12 | Y76: =IFERROR((X76-X$3)/(X$2-X$3), "") -> 0.58945386
D77: United Arab Emirates | E77: 72.46 | G77: Africa | H77: Gambia | I77: =IFERROR(( K77*'Best Country'!$E$12+ M77*'Best Country'!$E$15+ O77*'Best Country'!$E$18+ Q77*'Best Country'!$E$9+ S77*'Best Country'!$E$6+ U77*'Best Country'!$E$21+ W77*'Best Country'!$E$24+ Y77*'Best Country'!$E$27 )/SUM('Best Country'!$E$5:$E$28), "") | J77: 0.38757205 | K77: =IFERROR(1-(J77-J$3)/(J$2-J$3), "") -> 0.62311971 | L77: 0.524 | M77: =IFERROR((L77-L$3)/(L$2-L$3), "") -> 0.23287671 | N77: 65.86 | O77: =IFERROR((N77-N$3)/(N$2-N$3), "") -> 0.36480604 | P77: 982 | Q77: =IFERROR((P77-P$3)/(P$2-P$3), "") -> 0.0025118294 | S77: =IFERROR(1-(R77-R$3)/(R$2-R$3), "") | U77: =IFERROR((T77-T$3)/(T$2-T$3), "") | W77: =IFERROR(1-(V77-V$3)/(V$2-V$3), "") | X77: 4.423 | Y77: =IFERROR((X77-X$3)/(X$2-X$3), "") -> 0.48006905
D78: United Kingdom | E78: 65.85 | G78: Asia | H78: Georgia | I78: =IFERROR(( K78*'Best Country'!$E$12+ M78*'Best Country'!$E$15+ O78*'Best Country'!$E$18+ Q78*'Best Country'!$E$9+ S78*'Best Country'!$E$6+ U78*'Best Country'!$E$21+ W78*'Best Country'!$E$24+ Y78*'Best Country'!$E$27 )/SUM('Best Country'!$E$5:$E$28), "") -> 0.62591061 | J78: 0.34756896 | K78: =IFERROR(1-(J78-J$3)/(J$2-J$3), "") -> 0.72583186 | L78: 0.844 | M78: =IFERROR((L78-L$3)/(L$2-L$3), "") -> 0.78082192 | N78: 74.496 | O78: =IFERROR((N78-N$3)/(N$2-N$3), "") -> 0.64121111 | P78: 9287 | Q78: =IFERROR((P78-P$3)/(P$2-P$3), "") -> 0.03440899 | R78: 23.2 | S78: =IFERROR(1-(R78-R$3)/(R$2-R$3), "") -> 0.85662651 | T78: 74 | U78: =IFERROR((T78-T$3)/(T$2-T$3), "") -> 0.82952816 | V78: 56.4 | W78: =IFERROR(1-(V78-V$3)/(V$2-V$3), "") -> 0.64556962 | X78: 5.4 | Y78: =IFERROR((X78-X$3)/(X$2-X$3), "") -> 0.63339611
D79: United States | E79: 64.18 | G79: Europe | H79: Germany | I79: =IFERROR(( K79*'Best Country'!$E$12+ M79*'Best Country'!$E$15+ O79*'Best Country'!$E$18+ Q79*'Best Country'!$E$9+ S79*'Best Country'!$E$6+ U79*'Best Country'!$E$21+ W79*'Best Country'!$E$24+ Y79*'Best Country'!$E$27 )/SUM('Best Country'!$E$5:$E$28), "") -> 0.68108794 | J79: 0.3243345 | K79: =IFERROR(1-(J79-J$3)/(J$2-J$3), "") -> 0.78548879 | L79: 0.959 | M79: =IFERROR((L79-L$3)/(L$2-L$3), "") -> 0.97773973 | N79: 81.378 | O79: =IFERROR((N79-N$3)/(N$2-N$3), "") -> 0.8614774 | P79: 56435 | Q79: =IFERROR((P79-P$3)/(P$2-P$3), "") -> 0.21549115 | R79: 47.6 | S79: =IFERROR(1-(R79-R$3)/(R$2-R$3), "") -> 0.5626506 | T79: 60.4 | U79: =IFERROR((T79-T$3)/(T$2-T$3), "") -> 0.62252664 | V79: 71.7 | W79: =IFERROR(1-(V79-V$3)/(V$2-V$3), "") -> 0.32278481 | X79: 6.753 | Y79: =IFERROR((X79-X$3)/(X$2-X$3), "") -> 0.84573132
D80: Uruguay | E80: 60.41 | G80: Africa | H80: Ghana | I80: =IFERROR(( K80*'Best Country'!$E$12+ M80*'Best Country'!$E$15+ O80*'Best Country'!$E$18+ Q80*'Best Country'!$E$9+ S80*'Best Country'!$E$6+ U80*'Best Country'!$E$21+ W80*'Best Country'!$E$24+ Y80*'Best Country'!$E$27 )/SUM('Best Country'!$E$5:$E$28), "") | J80: 0.43508595 | K80: =IFERROR(1-(J80-J$3)/(J$2-J$3), "") -> 0.50112276 | L80: 0.628 | M80: =IFERROR((L80-L$3)/(L$2-L$3), "") -> 0.4109589 | N80: 65.498 | O80: =IFERROR((N80-N$3)/(N$2-N$3), "") -> 0.35321982 | P80: 2519 | Q80: =IFERROR((P80-P$3)/(P$2-P$3), "") -> 0.0084150126 | R80: 22.1 | S80: =IFERROR(1-(R80-R$3)/(R$2-R$3), "") -> 0.86987952 | U80: =IFERROR((T80-T$3)/(T$2-T$3), "") | W80: =IFERROR(1-(V80-V$3)/(V$2-V$3), "") | X80: 4.34 | Y80: =IFERROR((X80-X$3)/(X$2-X$3), "") -> 0.46704331
D81: Vietnam | E81: 60.66 | G81: Europe | H81: Gibraltar | I81: =IFERROR(( K81*'Best Country'!$E$12+ M81*'Best Country'!$E$15+ O81*'Best Country'!$E$18+ Q81*'Best Country'!$E$9+ S81*'Best Country'!$E$6+ U81*'Best Country'!$E$21+ W81*'Best Country'!$E$24+ Y81*'Best Country'!$E$27 )/SUM('Best Country'!$E$5:$E$28), "") | K81: =IFERROR(1-(J81-J$3)/(J$2-J$3), "") | M81: =IFERROR((L81-L$3)/(L$2-L$3), "") | O81: =IFERROR((N81-N$3)/(N$2-N$3), "") | Q81: =IFERROR((P81-P$3)/(P$2-P$3), "") | S81: =IFERROR(1-(R81-R$3)/(R$2-R$3), "") | U81: =IFERROR((T81-T$3)/(T$2-T$3), "") | W81: =IFERROR(1-(V81-V$3)/(V$2-V$3), "") | Y81: =IFERROR((X81-X$3)/(X$2-X$3), "")
G82: Europe | H82: Greece | I82: =IFERROR(( K82*'Best Country'!$E$12+ M82*'Best Country'!$E$15+ O82*'Best Country'!$E$18+ Q82*'Best Country'!$E$9+ S82*'Best Country'!$E$6+ U82*'Best Country'!$E$21+ W82*'Best Country'!$E$24+ Y82*'Best Country'!$E$27 )/SUM('Best Country'!$E$5:$E$28), "") -> 0.64829997 | J82: 0.333736 | K82: =IFERROR(1-(J82-J$3)/(J$2-J$3), "") -> 0.76134945 | L82: 0.908 | M82: =IFERROR((L82-L$3)/(L$2-L$3), "") -> 0.89041096 | N82: 81.857 | O82: =IFERROR((N82-N$3)/(N$2-N$3), "") -> 0.87680835 | P82: 26899 | Q82: =IFERROR((P82-P$3)/(P$2-P$3), "") -> 0.10205171 | R82: 34.4 | S82: =IFERROR(1-(R82-R$3)/(R$2-R$3), "") -> 0.72168675 | T82: 53.6 | U82: =IFERROR((T82-T$3)/(T$2-T$3), "") -> 0.51902588 | V82: 58.5 | W82: =IFERROR(1-(V82-V$3)/(V$2-V$3), "") -> 0.60126582 | X82: 5.776 | Y82: =IFERROR((X82-X$3)/(X$2-X$3), "") -> 0.69240427
G83: North America | H83: Greenland | I83: =IFERROR(( K83*'Best Country'!$E$12+ M83*'Best Country'!$E$15+ O83*'Best Country'!$E$18+ Q83*'Best Country'!$E$9+ S83*'Best Country'!$E$6+ U83*'Best Country'!$E$21+ W83*'Best Country'!$E$24+ Y83*'Best Country'!$E$27 )/SUM('Best Country'!$E$5:$E$28), "") | K83: =IFERROR(1-(J83-J$3)/(J$2-J$3), "") | M83: =IFERROR((L83-L$3)/(L$2-L$3), "") | O83: =IFERROR((N83-N$3)/(N$2-N$3), "") | P83: 54547 | Q83: =IFERROR((P83-P$3)/(P$2-P$3), "") -> 0.20823988 | S83: =IFERROR(1-(R83-R$3)/(R$2-R$3), "") | U83: =IFERROR((T83-T$3)/(T$2-T$3), "") | W83: =IFERROR(1-(V83-V$3)/(V$2-V$3), "") | Y83: =IFERROR((X83-X$3)/(X$2-X$3), "")
G84: North America | H84: Grenada | I84: =IFERROR(( K84*'Best Country'!$E$12+ M84*'Best Country'!$E$15+ O84*'Best Country'!$E$18+ Q84*'Best Country'!$E$9+ S84*'Best Country'!$E$6+ U84*'Best Country'!$E$21+ W84*'Best Country'!$E$24+ Y84*'Best Country'!$E$27 )/SUM('Best Country'!$E$5:$E$28), "") | J84: 0.4381641 | K84: =IFERROR(1-(J84-J$3)/(J$2-J$3), "") -> 0.49321929 | L84: 0.791 | M84: =IFERROR((L84-L$3)/(L$2-L$3), "") -> 0.69006849 | N84: 75.205 | O84: =IFERROR((N84-N$3)/(N$2-N$3), "") -> 0.66390347 | P84: 12480 | Q84: =IFERROR((P84-P$3)/(P$2-P$3), "") -> 0.046672402 | S84: =IFERROR(1-(R84-R$3)/(R$2-R$3), "") | U84: =IFERROR((T84-T$3)/(T$2-T$3), "") | W84: =IFERROR(1-(V84-V$3)/(V$2-V$3), "") | Y84: =IFERROR((X84-X$3)/(X$2-X$3), "")
G85: North America | H85: Guadeloupe | I85: =IFERROR(( K85*'Best Country'!$E$12+ M85*'Best Country'!$E$15+ O85*'Best Country'!$E$18+ Q85*'Best Country'!$E$9+ S85*'Best Country'!$E$6+ U85*'Best Country'!$E$21+ W85*'Best Country'!$E$24+ Y85*'Best Country'!$E$27 )/SUM('Best Country'!$E$5:$E$28), "") | K85: =IFERROR(1-(J85-J$3)/(J$2-J$3), "") | M85: =IFERROR((L85-L$3)/(L$2-L$3), "") | O85: =IFERROR((N85-N$3)/(N$2-N$3), "") | Q85: =IFERROR((P85-P$3)/(P$2-P$3), "") | S85: =IFERROR(1-(R85-R$3)/(R$2-R$3), "") | U85: =IFERROR((T85-T$3)/(T$2-T$3), "") | W85: =IFERROR(1-(V85-V$3)/(V$2-V$3), "") | Y85: =IFERROR((X85-X$3)/(X$2-X$3), "")
G86: Oceania | H86: Guam | I86: =IFERROR(( K86*'Best Country'!$E$12+ M86*'Best Country'!$E$15+ O86*'Best Country'!$E$18+ Q86*'Best Country'!$E$9+ S86*'Best Country'!$E$6+ U86*'Best Country'!$E$21+ W86*'Best Country'!$E$24+ Y86*'Best Country'!$E$27 )/SUM('Best Country'!$E$5:$E$28), "") | K86: =IFERROR(1-(J86-J$3)/(J$2-J$3), "") | M86: =IFERROR((L86-L$3)/(L$2-L$3), "") | O86: =IFERROR((N86-N$3)/(N$2-N$3), "") | Q86: =IFERROR((P86-P$3)/(P$2-P$3), "") | S86: =IFERROR(1-(R86-R$3)/(R$2-R$3), "") | U86: =IFERROR((T86-T$3)/(T$2-T$3), "") | W86: =IFERROR(1-(V86-V$3)/(V$2-V$3), "") | Y86: =IFERROR((X86-X$3)/(X$2-X$3), "")
G87: North America | H87: Guatemala | I87: =IFERROR(( K87*'Best Country'!$E$12+ M87*'Best Country'!$E$15+ O87*'Best Country'!$E$18+ Q87*'Best Country'!$E$9+ S87*'Best Country'!$E$6+ U87*'Best Country'!$E$21+ W87*'Best Country'!$E$24+ Y87*'Best Country'!$E$27 )/SUM('Best Country'!$E$5:$E$28), "") | J87: 0.45212683 | K87: =IFERROR(1-(J87-J$3)/(J$2-J$3), "") -> 0.45736851 | L87: 0.662 | M87: =IFERROR((L87-L$3)/(L$2-L$3), "") -> 0.46917808 | N87: 72.602 | O87: =IFERROR((N87-N$3)/(N$2-N$3), "") -> 0.58059147 | P87: 6484 | Q87: =IFERROR((P87-P$3)/(P$2-P$3), "") -> 0.023643458 | R87: 28 | S87: =IFERROR(1-(R87-R$3)/(R$2-R$3), "") -> 0.79879518 | U87: =IFERROR((T87-T$3)/(T$2-T$3), "") | W87: =IFERROR(1-(V87-V$3)/(V$2-V$3), "") | X87: 6.362 | Y87: =IFERROR((X87-X$3)/(X$2-X$3), "") -> 0.78436911
G88: Europe | H88: Guernsey | I88: =IFERROR(( K88*'Best Country'!$E$12+ M88*'Best Country'!$E$15+ O88*'Best Country'!$E$18+ Q88*'Best Country'!$E$9+ S88*'Best Country'!$E$6+ U88*'Best Country'!$E$21+ W88*'Best Country'!$E$24+ Y88*'Best Country'!$E$27 )/SUM('Best Country'!$E$5:$E$28), "") | K88: =IFERROR(1-(J88-J$3)/(J$2-J$3), "") | M88: =IFERROR((L88-L$3)/(L$2-L$3), "") | O88: =IFERROR((N88-N$3)/(N$2-N$3), "") | Q88: =IFERROR((P88-P$3)/(P$2-P$3), "") | R88: 62.5 | S88: =IFERROR(1-(R88-R$3)/(R$2-R$3), "") -> 0.38313253 | U88: =IFERROR((T88-T$3)/(T$2-T$3), "") | W88: =IFERROR(1-(V88-V$3)/(V$2-V$3), "") | Y88: =IFERROR((X88-X$3)/(X$2-X$3), "")
G89: Africa | H89: Guinea | I89: =IFERROR(( K89*'Best Country'!$E$12+ M89*'Best Country'!$E$15+ O89*'Best Country'!$E$18+ Q89*'Best Country'!$E$9+ S89*'Best Country'!$E$6+ U89*'Best Country'!$E$21+ W89*'Best Country'!$E$24+ Y89*'Best Country'!$E$27 )/SUM('Best Country'!$E$5:$E$28), "") | J89: 0.29591954 | K89: =IFERROR(1-(J89-J$3)/(J$2-J$3), "") -> 0.85844719 | L89: 0.5 | M89: =IFERROR((L89-L$3)/(L$2-L$3), "") -> 0.19178082 | N89: 60.74 | O89: =IFERROR((N89-N$3)/(N$2-N$3), "") -> 0.20093458 | P89: 1993 | Q89: =IFERROR((P89-P$3)/(P$2-P$3), "") -> 0.0063947951 | S89: =IFERROR(1-(R89-R$3)/(R$2-R$3), "") | U89: =IFERROR((T89-T$3)/(T$2-T$3), "") | W89: =IFERROR(1-(V89-V$3)/(V$2-V$3), "") | X89: 4.929 | Y89: =IFERROR((X89-X$3)/(X$2-X$3), "") -> 0.55947897
G90: Africa | H90: Guinea-Bissau | I90: =IFERROR(( K90*'Best Country'!$E$12+ M90*'Best Country'!$E$15+ O90*'Best Country'!$E$18+ Q90*'Best Country'!$E$9+ S90*'Best Country'!$E$6+ U90*'Best Country'!$E$21+ W90*'Best Country'!$E$24+ Y90*'Best Country'!$E$27 )/SUM('Best Country'!$E$5:$E$28), "") | J90: 0.33435068 | K90: =IFERROR(1-(J90-J$3)/(J$2-J$3), "") -> 0.75977119 | L90: 0.514 | M90: =IFERROR((L90-L$3)/(L$2-L$3), "") -> 0.21575342 | N90: 64.085 | O90: =IFERROR((N90-N$3)/(N$2-N$3), "") -> 0.30799514 | P90: 1011 | Q90: =IFERROR((P90-P$3)/(P$2-P$3), "") -> 0.0026232102 | S90: =IFERROR(1-(R90-R$3)/(R$2-R$3), "") | U90: =IFERROR((T90-T$3)/(T$2-T$3), "") | W90: =IFERROR(1-(V90-V$3)/(V$2-V$3), "") | Y90: =IFERROR((X90-X$3)/(X$2-X$3), "")
G91: South America | H91: Guyana | I91: =IFERROR(( K91*'Best Country'!$E$12+ M91*'Best Country'!$E$15+ O91*'Best Country'!$E$18+ Q91*'Best Country'!$E$9+ S91*'Best Country'!$E$6+ U91*'Best Country'!$E$21+ W91*'Best Country'!$E$24+ Y91*'Best Country'!$E$27 )/SUM('Best Country'!$E$5:$E$28), "") | K91: =IFERROR(1-(J91-J$3)/(J$2-J$3), "") | L91: 0.776 | M91: =IFERROR((L91-L$3)/(L$2-L$3), "") -> 0.66438356 | N91: 70.18 | O91: =IFERROR((N91-N$3)/(N$2-N$3), "") -> 0.50307259 | P91: 30888 | Q91: =IFERROR((P91-P$3)/(P$2-P$3), "") -> 0.11737233 | R91: 35.1 | S91: =IFERROR(1-(R91-R$3)/(R$2-R$3), "") -> 0.71325301 | U91: =IFERROR((T91-T$3)/(T$2-T$3), "") | W91: =IFERROR(1-(V91-V$3)/(V$2-V$3), "") | Y91: =IFERROR((X91-X$3)/(X$2-X$3), "")
G92: North America | H92: Haiti | I92: =IFERROR(( K92*'Best Country'!$E$12+ M92*'Best Country'!$E$15+ O92*'Best Country'!$E$18+ Q92*'Best Country'!$E$9+ S92*'Best Country'!$E$6+ U92*'Best Country'!$E$21+ W92*'Best Country'!$E$24+ Y92*'Best Country'!$E$27 )/SUM('Best Country'!$E$5:$E$28), "") | J92: 0.60450804 | K92: =IFERROR(1-(J92-J$3)/(J$2-J$3), "") -> 0.066113683 | L92: 0.554 | M92: =IFERROR((L92-L$3)/(L$2-L$3), "") -> 0.28424658 | N92: 64.936 | O92: =IFERROR((N92-N$3)/(N$2-N$3), "") -> 0.33523236 | P92: 2818 | Q92: =IFERROR((P92-P$3)/(P$2-P$3), "") -> 0.0095633872 | S92: =IFERROR(1-(R92-R$3)/(R$2-R$3), "") | U92: =IFERROR((T92-T$3)/(T$2-T$3), "") | W92: =IFERROR(1-(V92-V$3)/(V$2-V$3), "") | Y92: =IFERROR((X92-X$3)/(X$2-X$3), "")
G93: North America | H93: Honduras | I93: =IFERROR(( K93*'Best Country'!$E$12+ M93*'Best Country'!$E$15+ O93*'Best Country'!$E$18+ Q93*'Best Country'!$E$9+ S93*'Best Country'!$E$6+ U93*'Best Country'!$E$21+ W93*'Best Country'!$E$24+ Y93*'Best Country'!$E$27 )/SUM('Best Country'!$E$5:$E$28), "") | J93: 0.46826828 | K93: =IFERROR(1-(J93-J$3)/(J$2-J$3), "") -> 0.41592363 | L93: 0.645 | M93: =IFERROR((L93-L$3)/(L$2-L$3), "") -> 0.44006849 | N93: 72.884 | O93: =IFERROR((N93-N$3)/(N$2-N$3), "") -> 0.58961721 | P93: 3468 | Q93: =IFERROR((P93-P$3)/(P$2-P$3), "") -> 0.012059854 | R93: 24.1 | S93: =IFERROR(1-(R93-R$3)/(R$2-R$3), "") -> 0.84578313 | U93: =IFERROR((T93-T$3)/(T$2-T$3), "") | W93: =IFERROR(1-(V93-V$3)/(V$2-V$3), "") | X93: 5.964 | Y93: =IFERROR((X93-X$3)/(X$2-X$3), "") -> 0.72190835
G94: Asia | H94: Hong Kong | I94: =IFERROR(( K94*'Best Country'!$E$12+ M94*'Best Country'!$E$15+ O94*'Best Country'!$E$18+ Q94*'Best Country'!$E$9+ S94*'Best Country'!$E$6+ U94*'Best Country'!$E$21+ W94*'Best Country'!$E$24+ Y94*'Best Country'!$E$27 )/SUM('Best Country'!$E$5:$E$28), "") | K94: =IFERROR(1-(J94-J$3)/(J$2-J$3), "") | L94: 0.955 | M94: =IFERROR((L94-L$3)/(L$2-L$3), "") -> 0.97089041 | N94: 85.511 | O94: =IFERROR((N94-N$3)/(N$2-N$3), "") -> 0.9937588 | P94: 57328 | Q94: =IFERROR((P94-P$3)/(P$2-P$3), "") -> 0.21892091 | R94: 65.6 | S94: =IFERROR(1-(R94-R$3)/(R$2-R$3), "") -> 0.34578313 | T94: 78.5 | U94: =IFERROR((T94-T$3)/(T$2-T$3), "") -> 0.89802131 | V94: 66.5 | W94: =IFERROR(1-(V94-V$3)/(V$2-V$3), "") -> 0.43248945 | X94: 5.491 | Y94: =IFERROR((X94-X$3)/(X$2-X$3), "") -> 0.64767734
G95: Europe | H95: Hungary | I95: =IFERROR(( K95*'Best Country'!$E$12+ M95*'Best Country'!$E$15+ O95*'Best Country'!$E$18+ Q95*'Best Country'!$E$9+ S95*'Best Country'!$E$6+ U95*'Best Country'!$E$21+ W95*'Best Country'!$E$24+ Y95*'Best Country'!$E$27 )/SUM('Best Country'!$E$5:$E$28), "") -> 0.6616954 | J95: 0.30222824 | K95: =IFERROR(1-(J95-J$3)/(J$2-J$3), "") -> 0.84224894 | L95: 0.87 | M95: =IFERROR((L95-L$3)/(L$2-L$3), "") -> 0.82534247 | N95: 77.024 | O95: =IFERROR((N95-N$3)/(N$2-N$3), "") -> 0.72212265 | P95: 24612 | Q95: =IFERROR((P95-P$3)/(P$2-P$3), "") -> 0.09326799 | R95: 29.8 | S95: =IFERROR(1-(R95-R$3)/(R$2-R$3), "") -> 0.77710843 | T95: 66.3 | U95: =IFERROR((T95-T$3)/(T$2-T$3), "") -> 0.71232877 | V95: 54.1 | W95: =IFERROR(1-(V95-V$3)/(V$2-V$3), "") -> 0.69409283 | X95: 5.915 | Y95: =IFERROR((X95-X$3)/(X$2-X$3), "") -> 0.71421846
G96: Europe | H96: Iceland | I96: =IFERROR(( K96*'Best Country'!$E$12+ M96*'Best Country'!$E$15+ O96*'Best Country'!$E$18+ Q96*'Best Country'!$E$9+ S96*'Best Country'!$E$6+ U96*'Best Country'!$E$21+ W96*'Best Country'!$E$24+ Y96*'Best Country'!$E$27 )/SUM('Best Country'!$E$5:$E$28), "") -> 0.72725099 | J96: 0.2656501 | K96: =IFERROR(1-(J96-J$3)/(J$2-J$3), "") -> 0.93616717 | L96: 0.972 | M96: =IFERROR((L96-L$3)/(L$2-L$3), "") -> 1 | N96: 82.691 | O96: =IFERROR((N96-N$3)/(N$2-N$3), "") -> 0.90350147 | P96: 88657 | Q96: =IFERROR((P96-P$3)/(P$2-P$3), "") -> 0.33924676 | R96: 75.2 | S96: =IFERROR(1-(R96-R$3)/(R$2-R$3), "") -> 0.23012048 | T96: 74.2 | U96: =IFERROR((T96-T$3)/(T$2-T$3), "") -> 0.8325723 | V96: 67.9 | W96: =IFERROR(1-(V96-V$3)/(V$2-V$3), "") -> 0.40295359 | X96: 7.515 | Y96: =IFERROR((X96-X$3)/(X$2-X$3), "") -> 0.96531701
G97: Asia | H97: India | I97: =IFERROR(( K97*'Best Country'!$E$12+ M97*'Best Country'!$E$15+ O97*'Best Country'!$E$18+ Q97*'Best Country'!$E$9+ S97*'Best Country'!$E$6+ U97*'Best Country'!$E$21+ W97*'Best Country'!$E$24+ Y97*'Best Country'!$E$27 )/SUM('Best Country'!$E$5:$E$28), "") -> 0.54243132 | J97: 0.25514996 | K97: =IFERROR(1-(J97-J$3)/(J$2-J$3), "") -> 0.96312739 | L97: 0.685 | M97: =IFERROR((L97-L$3)/(L$2-L$3), "") -> 0.50856164 | N97: 72.003 | O97: =IFERROR((N97-N$3)/(N$2-N$3), "") -> 0.56141979 | P97: 2860 | Q97: =IFERROR((P97-P$3)/(P$2-P$3), "") -> 0.0097246974 | R97: 12.8 | S97: =IFERROR(1-(R97-R$3)/(R$2-R$3), "") -> 0.98192771 | T97: 55.8 | U97: =IFERROR((T97-T$3)/(T$2-T$3), "") -> 0.55251142 | V97: 65.5 | W97: =IFERROR(1-(V97-V$3)/(V$2-V$3), "") -> 0.4535865 | X97: 4.389 | Y97: =IFERROR((X97-X$3)/(X$2-X$3), "") -> 0.47473321
G98: Asia | H98: Indonesia | I98: =IFERROR(( K98*'Best Country'!$E$12+ M98*'Best Country'!$E$15+ O98*'Best Country'!$E$18+ Q98*'Best Country'!$E$9+ S98*'Best Country'!$E$6+ U98*'Best Country'!$E$21+ W98*'Best Country'!$E$24+ Y98*'Best Country'!$E$27 )/SUM('Best Country'!$E$5:$E$28), "") -> 0.56050274 | J98: 0.34894395 | K98: =IFERROR(1-(J98-J$3)/(J$2-J$3), "") -> 0.72230143 | L98: 0.728 | M98: =IFERROR((L98-L$3)/(L$2-L$3), "") -> 0.58219178 | N98: 71.146 | O98: =IFERROR((N98-N$3)/(N$2-N$3), "") -> 0.53399053 | P98: 5004 | Q98: =IFERROR((P98-P$3)/(P$2-P$3), "") -> 0.017959196 | R98: 17.6 | S98: =IFERROR(1-(R98-R$3)/(R$2-R$3), "") -> 0.92409639 | T98: 53.9 | U98: =IFERROR((T98-T$3)/(T$2-T$3), "") -> 0.52359209 | V98: 61.2 | W98: =IFERROR(1-(V98-V$3)/(V$2-V$3), "") -> 0.5443038 | X98: 5.617 | Y98: =IFERROR((X98-X$3)/(X$2-X$3), "") -> 0.66745135
G99: Asia | H99: Iran | I99: =IFERROR(( K99*'Best Country'!$E$12+ M99*'Best Country'!$E$15+ O99*'Best Country'!$E$18+ Q99*'Best Country'!$E$9+ S99*'Best Country'!$E$6+ U99*'Best Country'!$E$21+ W99*'Best Country'!$E$24+ Y99*'Best Country'!$E$27 )/SUM('Best Country'!$E$5:$E$28), "") -> 0.59205146 | J99: 0.35884795 | K99: =IFERROR(1-(J99-J$3)/(J$2-J$3), "") -> 0.69687187 | L99: 0.799 | M99: =IFERROR((L99-L$3)/(L$2-L$3), "") -> 0.70376712 | N99: 77.654 | O99: =IFERROR((N99-N$3)/(N$2-N$3), "") -> 0.74228652 | P99: 3690 | Q99: =IFERROR((P99-P$3)/(P$2-P$3), "") -> 0.012912493 | R99: 16.2 | S99: =IFERROR(1-(R99-R$3)/(R$2-R$3), "") -> 0.94096386 | T99: 49.5 | U99: =IFERROR((T99-T$3)/(T$2-T$3), "") -> 0.456621 | V99: 52.7 | W99: =IFERROR(1-(V99-V$3)/(V$2-V$3), "") -> 0.72362869 | X99: 5.093 | Y99: =IFERROR((X99-X$3)/(X$2-X$3), "") -> 0.58521657
G100: Asia | H100: Iraq | I100: =IFERROR(( K100*'Best Country'!$E$12+ M100*'Best Country'!$E$15+ O100*'Best Country'!$E$18+ Q100*'Best Country'!$E$9+ S100*'Best Country'!$E$6+ U100*'Best Country'!$E$21+ W100*'Best Country'!$E$24+ Y100*'Best Country'!$E$27 )/SUM('Best Country'!$E$5:$E$28), "") | J100: 0.2977404 | K100: =IFERROR(1-(J100-J$3)/(J$2-J$3), "") -> 0.85377194 | L100: 0.695 | M100: =IFERROR((L100-L$3)/(L$2-L$3), "") -> 0.52568493 | N100: 72.324 | O100: =IFERROR((N100-N$3)/(N$2-N$3), "") -> 0.57169377 | P100: 5487 | Q100: =IFERROR((P100-P$3)/(P$2-P$3), "") -> 0.019814263 | R100: 18.3 | S100: =IFERROR(1-(R100-R$3)/(R$2-R$3), "") -> 0.91566265 | U100: =IFERROR((T100-T$3)/(T$2-T$3), "") | W100: =IFERROR(1-(V100-V$3)/(V$2-V$3), "") | X100: 4.976 | Y100: =IFERROR((X100-X$3)/(X$2-X$3), "") -> 0.56685499
G101: Europe | H101: Ireland | I101: =IFERROR(( K101*'Best Country'!$E$12+ M101*'Best Country'!$E$15+ O101*'Best Country'!$E$18+ Q101*'Best Country'!$E$9+ S101*'Best Country'!$E$6+ U101*'Best Country'!$E$21+ W101*'Best Country'!$E$24+ Y101*'Best Country'!$E$27 )/SUM('Best Country'!$E$5:$E$28), "") -> 0.72600608 | J101: 0.2991203 | K101: =IFERROR(1-(J101-J$3)/(J$2-J$3), "") -> 0.8502289 | L101: 0.949 | M101: =IFERROR((L101-L$3)/(L$2-L$3), "") -> 0.96061644 | N101: 82.412 | O101: =IFERROR((N101-N$3)/(N$2-N$3), "") -> 0.89457176 | P101: 112818 | Q101: =IFERROR((P101-P$3)/(P$2-P$3), "") -> 0.43204234 | R101: 57 | S101: =IFERROR(1-(R101-R$3)/(R$2-R$3), "") -> 0.44939759 | T101: 51.4 | U101: =IFERROR((T101-T$3)/(T$2-T$3), "") -> 0.48554033 | V101: 51.5 | W101: =IFERROR(1-(V101-V$3)/(V$2-V$3), "") -> 0.74894515 | X101: 6.889 | Y101: =IFERROR((X101-X$3)/(X$2-X$3), "") -> 0.8670747
...

Sheet Best Country (diagrams)

Sheet Correlations

Sheet Correlations (help)

Sheet Data
A1: Alpha-2-Code | B1: Alpha-3-Code | C1: Country | D1: Continent | E1: UN-Member? | F1: Currency | G1: Population | H1: Big Mac Index (% under-/overvalued; raw index) | I1: Big Mac Index (% under-/overvalued; GDP-adjusted) | J1: GDP (IMF '25; USD) | K1: GDP (UN '23; USD) | L1: GDP per capita (USD) | M1: Year of Gini-survey | N1: Gini-Coefficient (2021 prices; income or consumption consolid) | O1: HDI (2023) | P1: Years of life expectancy at birth (2023) | Q1: Expected years of schooling (2023) | R1: Mean years of schooling (2023) | S1: GNI per capita (USD) | T1: Cost of Living Index | U1: Rent Index | V1: Cost of Living Plus Rent Index | W1: Groceries Index | X1: Restaurant Price Index | Y1: Local Purchasing Power Index | Z1: Price To Income Ratio | AA1: Gross Rental Yield City Centre | AB1: Gross Rental Yield Outside of Centre | AC1: Price To Rent Ratio City Centre | AD1: Price To Rent Ratio Outside Of City Centre | AE1: Mortgage As A Percentage Of Income | AF1: Affordability Index | AG1: Quality of Life Index | AH1: Purchasing Power Index | AI1: Safety Index | AJ1: Health Care Index | AK1: Property Price to Income Ratio | AL1: Traffic Commute Time Index | AM1: Pollution Index | AN1: Climate Index | AO1: Word Happieness Report (life evaluation; 3-year-average)
A2: AF | C2: Afghanistan | D2: Asia | E2: TRUE | G2: 43844100 | K2: 16420000000 | L2: 374 | O2: 0.496 | P2: 66.035 | Q2: 10.790143 | R2: 2.5147901 | S2: 1971.5495 | T2: 19.1 | U2: 2 | V2: 11.6 | W2: 16.6 | X2: 13.2 | Y2: 35.7 | AO2: 1.364
A3: AL | B3: ALB | C3: Albania | D3: Europe | E3: TRUE | G3: 2771510 | J3: 28370000000 | K3: 22980000000 | L3: 10237 | M3: 2020 | N3: 0.2941963 | O3: 0.81 | P3: 79.602 | Q3: 14.51015 | R3: 10.175311 | S3: 17627.394 | T3: 43.7 | U3: 15.3 | V3: 31.3 | W3: 44.1 | X3: 40.7 | Y3: 45.1 | Z3: 16.3 | AA3: 4.9 | AB3: 5.7 | AC3: 20.3 | AD3: 17.4 | AE3: 135.1 | AF3: 0.7 | AG3: 104.1 | AH3: 46.3 | AI3: 55.8 | AJ3: 48.2 | AK3: 16.3 | AL3: 36.3 | AM3: 77.3 | AN3: 86.3 | AO3: 5.411
A4: DZ | B4: DZA | C4: Algeria | D4: Africa | E4: TRUE | G4: 47435300 | J4: 268880000000 | K4: 247630000000 | L4: 5668 | M4: 2011 | N4: 0.27615732 | O4: 0.763 | P4: 76.261 | Q4: 15.49516 | R4: 7.416387 | S4: 15114.172 | T4: 26.8 | U4: 3.8 | V4: 16.7 | W4: 36 | X4: 15.4 | Y4: 38.3 | Z4: 16.5 | AA4: 2.8 | AB4: 3 | AC4: 35.2 | AD4: 33.4 | AE4: 143.1 | AF4: 0.7 | AO4: 5.571
A5: AS | C5: American Samoa | D5: Oceania | E5: FALSE
A6: AD | C6: Andorra | D6: Europe | E6: TRUE | G6: 82904 | J6: 4040000000 | K6: 3790000000 | L6: 48671 | O6: 0.913 | P6: 84.041 | Q6: 14.54279 | R6: 11.61 | S6: 64631.075
A7: AO | B7: AGO | C7: Angola | D7: Africa | E7: TRUE | G7: 39040000 | J7: 113340000000 | K7: 90550000000 | L7: 2903 | M7: 2018 | N7: 0.51264286 | O7: 0.616 | P7: 64.617 | Q7: 12.1676 | R7: 5.956173 | S7: 6631.2765
A8: AI | C8: Anguilla | D8: North America | E8: FALSE | G8: 14728 | K8: 415740000 | L8: 28228
A9: AG | C9: Antigua and Barbuda | D9: North America | E9: TRUE | G9: 94209 | J9: 2370000000 | K9: 2030000000 | L9: 25189 | O9: 0.851 | P9: 77.598 | Q9: 15.502999 | R9: 11.6475 | S9: 27386.518
A10: AR | B10: ARG | C10: Argentina | D10: South America | E10: TRUE | F10: Peso | G10: 45851400 | H10: -14.6 | I10: 17 | J10: 683530000000 | K10: 646080000000 | L10: 14908 | M10: 2023 | N10: 0.42390975 | O10: 0.865 | P10: 77.395 | Q10: 18.831209 | R10: 11.184582 | S10: 25876.053 | T10: 38.3 | U10: 11.5 | V10: 26.6 | W10: 38.6 | X10: 43.1 | Y10: 48.3 | Z10: 15.2 | AA10: 4.8 | AB10: 4.6 | AC10: 20.8 | AD10: 21.9 | AE10: 996.2 | AF10: 0.1 | AG10: 122.1 | AH10: 49.3 | AI10: 36.7 | AJ10: 67.9 | AK10: 15.2 | AL10: 43.8 | AM10: 50.8 | AN10: 94.9 | AO10: 6.397
A11: AM | B11: ARM | C11: Armenia | D11: Asia | E11: TRUE | G11: 2952360 | J11: 26260000000 | K11: 24220000000 | L11: 8894 | M11: 2023 | N11: 0.2715465 | O11: 0.811 | P11: 75.683 | Q11: 14.38385 | R11: 11.344978 | S11: 20220.723 | T11: 40.5 | U11: 15.7 | V11: 29.7 | W11: 35.4 | X11: 40.3 | Y11: 41.6 | Z11: 20.9 | AA11: 4.4 | AB11: 6 | AC11: 22.5 | AD11: 16.5 | AE11: 340 | AF11: 0.3 | AG11: 120.2 | AH11: 42.7 | AI11: 77.6 | AJ11: 60 | AK11: 20.9 | AL11: 29.3 | AM11: 61.8 | AN11: 63.4 | AO11: 5.494
A12: AW | C12: Aruba | D12: North America | E12: FALSE | G12: 108147 | J12: 4100000000 | K12: 3650000000 | L12: 37911
A13: AU | B13: AUS | C13: Australia | D13: Oceania | E13: TRUE | F13: A$ | G13: 26974000 | H13: -13.2 | I13: -9.8 | J13: 1770000000000 | K13: 1780000000000 | L13: 65681 | M13: 2018 | N13: 0.34332526 | O13: 0.958 | P13: 83.923 | Q13: 20.654779 | R13: 12.87 | S13: 58276.876 | T13: 63 | U13: 32.1 | V13: 49.5 | W13: 71.1 | X13: 58.3 | Y13: 143.8 | Z13: 8.4 | AA13: 4.3 | AB13: 4.4 | AC13: 23.3 | AD13: 22.6 | AE13: 74 | AF13: 1.4 | AG13: 195.1 | AH13: 148.7 | AI13: 52.6 | AJ13: 73.1 | AK13: 8.4 | AL13: 37.4 | AM13: 26.9 | AN13: 94.2 | AO13: 6.974
A14: AT | B14: AUT | C14: Austria | D14: Europe | E14: TRUE | G14: 9113570 | J14: 534300000000 | K14: 511690000000 | L14: 58627 | M14: 2022 | N14: 0.3089293 | O14: 0.93 | P14: 81.956 | Q14: 16.284281 | R14: 12.361465 | S14: 63479.208 | T14: 67.6 | U14: 25 | V14: 49.1 | W14: 68.6 | X14: 63.6 | Y14: 118.9 | Z14: 11.8 | AA14: 2.8 | AB14: 3.1 | AC14: 35.3 | AD14: 32.7 | AE14: 83.4 | AF14: 1.2 | AG14: 197.7 | AH14: 122 | AI14: 71.7 | AJ14: 78.5 | AK14: 11.8 | AL14: 23.2 | AM14: 20.6 | AN14: 76.6 | AO14: 6.81
A15: AZ | C15: Azerbaijan | D15: Asia | E15: TRUE | F15: Manat | G15: 10397700 | H15: -36.8 | I15: -13.5 | J15: 78870000000 | K15: 72360000000 | L15: 7585 | O15: 0.789 | P15: 74.429 | Q15: 12.90978 | R15: 11.07 | S15: 20667.957 | T15: 29.3 | U15: 9.6 | V15: 20.7 | W15: 27.8 | X15: 32.6 | Y15: 44.1 | Z15: 16.8 | AA15: 4.9 | AB15: 5 | AC15: 20.4 | AD15: 19.9 | AE15: 180.6 | AF15: 0.6 | AG15: 114.4 | AH15: 45.1 | AI15: 68.2 | AJ15: 49.1 | AK15: 16.8 | AL15: 40.2 | AM15: 72 | AN15: 91.4 | AO15: 4.875
A16: BS | C16: Bahamas | D16: North America | E16: TRUE | G16: 403033 | J16: 15180000000 | K16: 14340000000 | L16: 37659 | O16: 0.82 | P16: 74.552 | Q16: 11.89138 | R16: 12.814419 | S16: 30974.681 | T16: 85.4 | U16: 47.1 | V16: 68.7 | W16: 88.7 | X16: 89.6 | Y16: 62.8
A17: BH | C17: Bahrain | D17: Asia | E17: TRUE | F17: Dinar | G17: 1643330 | H17: -20.6 | I17: -3.3 | J17: 47830000000 | K17: 44660000000 | L17: 29105 | O17: 0.899 | P17: 81.284 | Q17: 15.92719 | R17: 11.13 | S17: 52818.795 | T17: 46.1 | U17: 21.1 | V17: 35.2 | W17: 43.8 | X17: 43.8 | Y17: 125 | AO17: 6.03
A18: BD | B18: BGD | C18: Bangladesh | D18: Asia | E18: TRUE | G18: 175687000 | J18: 467220000000 | K18: 422430000000 | L18: 2659 | M18: 2022 | N18: 0.33373156 | O18: 0.685 | P18: 74.672 | Q18: 12.310168 | R18: 6.79 | S18: 8497.6586 | T18: 21.2 | U18: 2.4 | V18: 13 | W18: 25.6 | X18: 15.3 | Y18: 38.9 | Z18: 11.5 | AA18: 3.2 | AB18: 3.1 | AC18: 31.7 | AD18: 32.2 | AE18: 134.4 | AF18: 0.7 | AG18: 77 | AH18: 39.3 | AI18: 38.5 | AJ18: 41.7 | AK18: 11.5 | AL18: 56.5 | AM18: 85.6 | AN18: 72.9 | AO18: 3.851
A19: BB | B19: BRB | C19: Barbados | D19: North America | E19: TRUE | G19: 282623 | J19: 7550000000 | K19: 6720000000 | L19: 26721 | M19: 2016 | N19: 0.34068036 | O19: 0.811 | P19: 76.178 | Q19: 16.628002 | R19: 9.9283569 | S19: 17327.52
A20: BY | B20: BLR | C20: Belarus | D20: Europe | E20: TRUE | G20: 8997600 | J20: 71560000000 | K20: 71860000000 | L20: 7953 | M20: 2020 | N20: 0.24383356 | O20: 0.824 | P20: 74.434 | Q20: 13.71881 | R20: 12.335373 | S20: 26724.871 | T20: 25.3 | U20: 9.5 | V20: 18.4 | W20: 25.5 | X20: 25.9 | Y20: 65.7 | Z20: 12.6 | AA20: 5 | AB20: 5 | AC20: 20.1 | AD20: 19.9 | AE20: 200.3 | AF20: 0.5 | AG20: 134.8 | AH20: 67.4 | AI20: 50.9 | AJ20: 49.3 | AK20: 12.6 | AL20: 31.3 | AM20: 44.5 | AN20: 69.3
A21: BE | B21: BEL | C21: Belgium | D21: Europe | E21: TRUE | G21: 11758600 | J21: 684860000000 | K21: 644780000000 | L21: 58244 | M21: 2022 | N21: 0.26375556 | O21: 0.951 | P21: 82.115 | Q21: 18.996031 | R21: 12.68965 | S21: 63582.475 | T21: 63.6 | U21: 22.8 | V21: 45.9 | W21: 61.9 | X21: 71.4 | Y21: 127.7 | Z21: 6.6 | AA21: 4.7 | AB21: 5.1 | AC21: 21.4 | AD21: 19.6 | AE21: 46.6 | AF21: 2.1 | AG21: 173.7 | AH21: 131 | AI21: 50.5 | AJ21: 75.8 | AK21: 6.6 | AL21: 34.5 | AM21: 49.2 | AN21: 86.4 | AO21: 6.91
A22: BZ | B22: BLZ | C22: Belize | D22: North America | E22: TRUE | G22: 422924 | J22: 3610000000 | K22: 3080000000 | L22: 8538 | M22: 2018 | N22: 0.39949584 | O22: 0.721 | P22: 73.566 | Q22: 11.9838 | R22: 8.76229 | S22: 12343.078 | T22: 42.3 | U22: 10.2 | V22: 28.3 | W22: 47.5 | X22: 33.8 | Y22: 78 | AO22: 6.711
A23: BJ | B23: BEN | C23: Benin | D23: Africa | E23: TRUE | G23: 14814500 | J23: 22240000000 | K23: 19670000000 | L23: 1501 | M23: 2021 | N23: 0.34395808 | O23: 0.515 | P23: 60.774 | Q23: 10.44648 | R23: 3.1942 | S23: 3805.5275 | AO23: 4.357
A24: BM | C24: Bermuda | D24: North America | E24: FALSE | G24: 64555 | K24: 8140000000 | L24: 126120
A25: BT | B25: BTN | C25: Bhutan | D25: Asia | E25: TRUE | G25: 796682 | J25: 3420000000 | K25: 3020000000 | L25: 4295 | M25: 2022 | N25: 0.2845992 | O25: 0.698 | P25: 72.975 | Q25: 13.152742 | R25: 5.8357947 | S25: 13842.804
A26: BO | B26: BOL | C26: Bolivia | D26: South America | E26: TRUE | G26: 12581800 | J26: 56340000000 | K26: 45140000000 | L26: 4478 | M26: 2023 | N26: 0.42050114 | O26: 0.733 | P26: 68.581 | Q26: 15.61065 | R26: 10.021223 | S26: 9445.2449 | T26: 25.5 | U26: 8.6 | V26: 18.1 | W26: 26.6 | X26: 20.7 | Y26: 45.6 | Z26: 12.6 | AA26: 7 | AB26: 6.1 | AC26: 14.3 | AD26: 16.4 | AE26: 121.1 | AF26: 0.8 | AO26: 5.868
A27: BA | B27: BIH | C27: Bosnia and Herzegovina | D27: Europe | E27: TRUE | G27: 3140100 | J27: 28810000000 | K27: 27510000000 | L27: 9174 | M27: 2011 | N27: 0.33030185 | O27: 0.804 | P27: 77.85 | Q27: 13.16394 | R27: 10.97 | S27: 19827.486 | T27: 35.7 | U27: 7.3 | V27: 23.4 | W27: 36.7 | X27: 28.2 | Y27: 67.3 | Z27: 13.2 | AA27: 2.9 | AB27: 2.9 | AC27: 34.8 | AD27: 34.4 | AE27: 101.7 | AF27: 1 | AG27: 136.8 | AH27: 68.4 | AI27: 58.8 | AJ27: 54.9 | AK27: 13.2 | AL27: 25.9 | AM27: 59.7 | AN27: 82.9 | AO27: 6.136
A28: BW | B28: BWA | C28: Botswana | D28: Africa | E28: TRUE | G28: 2562120 | J28: 19400000000 | K28: 19400000000 | L28: 7572 | M28: 2015 | N28: 0.5490736 | O28: 0.731 | P28: 69.163 | Q28: 11.42568 | R28: 10.478 | S28: 16983.771 | T28: 41.7 | U28: 6.1 | V28: 26.2 | W28: 29.9 | X28: 26.6 | Y28: 72.1 | AO28: 3.438
A29: BR | B29: BRA | C29: Brazil | D29: South America | E29: TRUE | F29: Real | G29: 212812000 | H29: -28.4 | I29: -3.2 | J29: 2130000000000 | K29: 2190000000000 | L29: 9990 | M29: 2023 | N29: 0.5163944 | O29: 0.786 | P29: 75.848 | Q29: 15.79271 | R29: 8.4253718 | S29: 18011.285 | T29: 28.6 | U29: 8.2 | V29: 19.7 | W29: 29.1 | X29: 23.8 | Y29: 46.6 | Z29: 15.1 | AA29: 4.7 | AB29: 4.6 | AC29: 21.3 | AD29: 21.6 | AE29: 189.8 | AF29: 0.5 | AG29: 117.8 | AH29: 47.6 | AI29: 35.8 | AJ29: 59.2 | AK29: 15.1 | AL29: 40.5 | AM29: 52.8 | AN29: 91.8 | AO29: 6.494
A30: VG | C30: British Virgin Islands | D30: North America | E30: FALSE | G30: 39732 | K30: 1510000000 | L30: 37900
A31: BN | C31: Brunei | D31: Asia | E31: TRUE | G31: 466330 | J31: 16010000000 | K31: 15130000000 | L31: 34325 | O31: 0.837 | P31: 75.327 | Q31: 13.69862 | R31: 9.282 | S31: 75826.873 | T31: 46.1 | U31: 17 | V31: 33.4 | W31: 65.9 | X31: 29 | Y31: 136.8
A32: BG | B32: BGR | C32: Bulgaria | D32: Europe | E32: TRUE | G32: 6714560 | J32: 117010000000 | K32: 102400000000 | L32: 17426 | M32: 2022 | N32: 0.38201502 | O32: 0.845 | P32: 75.636 | Q32: 15.31664 | R32: 11.454531 | S32: 32174.93 | T32: 39.3 | U32: 11.7 | V32: 27.3 | W32: 40.5 | X32: 38.7 | Y32: 86.3 | Z32: 9.1 | AA32: 4.3 | AB32: 4.6 | AC32: 23.4 | AD32: 21.7 | AE32: 65.8 | AF32: 1.5 | AG32: 148.3 | AH32: 88.2 | AI32: 64.1 | AJ32: 58.2 | AK32: 9.1 | AL32: 29.1 | AM32: 62.8 | AN32: 81.5 | AO32: 5.554
A33: BF | B33: BFA | C33: Burkina Faso | D33: Africa | E33: TRUE | G33: 24074600 | J33: 27060000000 | K33: 20320000000 | L33: 1124 | M33: 2021 | N33: 0.37391287 | O33: 0.459 | P33: 61.092 | Q33: 8.7333403 | R33: 2.2665501 | S33: 2390.5278 | AO33: 4.383
A34: BI | B34: BDI | C34: Burundi | D34: Africa | E34: TRUE | G34: 14390000 | J34: 6750000000 | K34: 3960000000 | L34: 469 | M34: 2020 | N34: 0.37456086 | O34: 0.439 | P34: 63.651 | Q34: 9.8294239 | R34: 3.4739356 | S34: 858.91557
A35: KH | C35: Cambodia | D35: Asia | E35: TRUE | G35: 17848000 | J35: 49800000000 | K35: 42820000000 | L35: 2790 | O35: 0.606 | P35: 70.668 | Q35: 11.197892 | R35: 5.1971002 | S35: 4931.0168 | T35: 33 | U35: 9.1 | V35: 22.6 | W35: 40 | X35: 22.6 | Y35: 30.3 | AO35: 4.341
A36: CM | B36: CMR | C36: Cameroon | D36: Africa | E36: TRUE | G36: 29879300 | J36: 56010000000 | K36: 49280000000 | L36: 1875 | M36: 2021 | N36: 0.42176074 | O36: 0.588 | P36: 63.7 | Q36: 10.79188 | R36: 6.5741804 | S36: 4746.2658 | T36: 39.6 | U36: 18.7 | V36: 30.5 | W36: 36.5 | X36: 45.7 | Y36: 10.7 | Z36: 46.7 | AA36: 9.1 | AB36: 10.5 | AC36: 11 | AD36: 9.6 | AE36: 909.8 | AF36: 0.1 | AO36: 4.887
A37: CA | B37: CAN | C37: Canada | D37: North America | E37: TRUE | F37: C$ | G37: 40126700 | H37: -9 | I37: 0.4 | J37: 2230000000000 | K37: 2140000000000 | L37: 55458 | M37: 2020 | N37: 0.29851684 | O37: 0.939 | P37: 82.63 | Q37: 15.88826 | R37: 13.87 | S37: 54688.417 | T37: 60.7 | U37: 31.9 | V37: 48.1 | W37: 67.5 | X37: 59 | Y37: 119.4 | Z37: 9.4 | AA37: 4.4 | AB37: 5.3 | AC37: 22.8 | AD37: 18.8 | AE37: 83.3 | AF37: 1.2 | AG37: 170.5 | AH37: 123.6 | AI37: 54.2 | AJ37: 68.6 | AK37: 9.4 | AL37: 33.5 | AM37: 29.8 | AN37: 55.9 | AO37: 6.803
A38: CV | B38: CPV | C38: Cape Verde | D38: Africa | E38: TRUE | G38: 527326 | J38: 2790000000 | K38: 2590000000 | L38: 5283 | M38: 2015 | N38: 0.42381087 | O38: 0.668 | P38: 76.059 | Q38: 11.367097 | R38: 6.090039 | S38: 8165.3792
A39: KY | C39: Cayman Islands | D39: North America | E39: FALSE | G39: 75844 | K39: 7130000000 | L39: 93972 | T39: 108.2 | U39: 76.3 | V39: 94.3 | W39: 113.9 | X39: 96.6 | Y39: 149.7
A40: CF | B40: CAF | C40: Central African Republic | D40: Africa | E40: TRUE | G40: 5513280 | J40: 2930000000 | K40: 2560000000 | L40: 532 | M40: 2021 | N40: 0.43034458 | O40: 0.414 | P40: 57.408 | Q40: 7.4357678 | R40: 3.9894315 | S40: 1099.8607
A41: TD | B41: TCD | C41: Chad | D41: Africa | E41: TRUE | G41: 21003700 | J41: 18790000000 | K41: 17640000000 | L41: 895 | M41: 2022 | N41: 0.37357685 | O41: 0.416 | P41: 55.069 | Q41: 8.3475902 | R41: 2.3349849 | S41: 1748.001 | AO41: 4.384
A42: CL | B42: CHL | C42: Chile | D42: South America | E42: TRUE | F42: Peso | G42: 19859900 | H42: -22.6 | I42: 1.2 | J42: 343820000000 | K42: 335530000000 | L42: 17312 | M42: 2022 | N42: 0.43042782 | O42: 0.878 | P42: 81.167 | Q42: 16.91242 | R42: 11.291054 | S42: 28047.17 | T42: 35.8 | U42: 11.3 | V42: 25.1 | W42: 38.9 | X42: 34.3 | Y42: 56.7 | Z42: 15 | AA42: 4.6 | AB42: 3.9 | AC42: 21.7 | AD42: 25.8 | AE42: 119.5 | AF42: 0.8 | AG42: 112.1 | AH42: 58.1 | AI42: 39.5 | AJ42: 63.7 | AK42: 15 | AL42: 36.2 | AM42: 77.4 | AN42: 95.6 | AO42: 6.361
A43: CN | B43: CHN | C43: China | D43: Asia | E43: TRUE | F43: Yuan | G43: 1416100000 | H43: -40.9 | I43: -23.4 | J43: 19230000000000 | K43: 17790000000000 | L43: 13581 | M43: 2021 | N43: 0.35743752 | O43: 0.797 | P43: 77.953 | Q43: 15.478749 | R43: 8.0361816 | S43: 22029.223 | T43: 29.4 | U43: 10.6 | V43: 21.2 | W43: 33.5 | X43: 19.9 | Y43: 88.1 | Z43: 25.2 | AA43: 1.6 | AB43: 2 | AC43: 61.5 | AD43: 50.1 | AE43: 184.3 | AF43: 0.5 | AG43: 127.7 | AH43: 90.4 | AI43: 76.5 | AJ43: 68.7 | AK43: 25.2 | AL43: 38.7 | AM43: 76.7 | AN43: 73.6 | AO43: 5.921
A44: CO | B44: COL | C44: Colombia | D44: South America | E44: TRUE | F44: Peso | G44: 53425600 | H44: -5.2 | I44: 31.7 | J44: 427770000000 | K44: 363540000000 | L44: 8007 | M44: 2023 | N44: 0.53881925 | O44: 0.788 | P44: 77.725 | Q44: 14.28641 | R44: 9.0315816 | S44: 18665.95 | T44: 28 | U44: 9.4 | V44: 19.9 | W44: 29.4 | X44: 23.1 | Y44: 41 | Z44: 17.4 | AA44: 5.1 | AB44: 5.5 | AC44: 19.7 | AD44: 18.1 | AE44: 239.6 | AF44: 0.4 | AG44: 106.3 | AH44: 42 | AI44: 39 | AJ44: 68.9 | AK44: 17.4 | AL44: 46.7 | AM44: 62.2 | AN44: 82.3 | AO44: 6.004
A45: KM | B45: COM | C45: Comoros | D45: Africa | E45: TRUE | G45: 882847 | J45: 1550000000 | K45: 1450000000 | L45: 1753 | M45: 2014 | N45: 0.45332187 | O45: 0.603 | P45: 66.777 | Q45: 13.294461 | R45: 6.0068402 | S45: 3481.1214 | AO45: 3.754
A46: CK | C46: Cook Islands | D46: Oceania | E46: FALSE | G46: 13263 | K46: 366210000 | L46: 27612
A47: CR | B47: CRI | C47: Costa Rica | D47: North America | E47: TRUE | F47: Colón | G47: 5152950 | H47: -1 | I47: 30.8 | J47: 102590000000 | K47: 86500000000 | L47: 19909 | M47: 2024 | N47: 0.4582914 | O47: 0.833 | P47: 80.799 | Q47: 16.349637 | R47: 8.8447525 | S47: 23417.213 | T47: 50.3 | U47: 18.9 | V47: 36.6 | W47: 56.5 | X47: 45.1 | Y47: 55.1 | Z47: 9.9 | AA47: 6.9 | AB47: 8.7 | AC47: 14.5 | AD47: 11.5 | AE47: 118.8 | AF47: 0.8 | AG47: 130.2 | AH47: 56.6 | AI47: 46.3 | AJ47: 65.1 | AK47: 9.9 | AL47: 60 | AM47: 41.6 | AN47: 93.1 | AO47: 7.274
A48: HR | B48: HRV | C48: Croatia | D48: Europe | E48: TRUE | G48: 3848160 | J48: 98950000000 | K48: 84390000000 | L48: 25714 | M48: 2022 | N48: 0.30017322 | O48: 0.889 | P48: 78.58 | Q48: 16.34815 | R48: 12.095122 | S48: 41379.89 | T48: 48.6 | U48: 17.3 | V48: 35 | W48: 45.2 | X48: 50.2 | Y48: 95.6 | Z48: 12.1 | AA48: 3.4 | AB48: 3.6 | AC48: 29.5 | AD48: 27.7 | AE48: 90.8 | AF48: 1.1 | AG48: 181.7 | AH48: 98.1 | AI48: 74.6 | AJ48: 64.8 | AK48: 12.1 | AL48: 25.2 | AM48: 31.6 | AN48: 89.9 | AO48: 5.87
A49: CU | C49: Cuba | D49: North America | E49: TRUE | G49: 10937200 | K49: 201990000000 | L49: 18468 | O49: 0.762 | P49: 78.085 | Q49: 13.87884 | R49: 10.631489 | S49: 8415.4117 | T49: 40.1 | U49: 11.8 | V49: 27.8 | W49: 40 | X49: 24.4 | Y49: 2.7 | Z49: 48.9 | AA49: 24.4 | AB49: 28.3 | AC49: 4.1 | AD49: 3.5 | AE49: 526.7 | AF49: 0.2
A50: CW | C50: Curacao | D50: North America | E50: FALSE | G50: 185487 | K50: 3280000000 | L50: 17691
A51: CY | B51: CYP | C51: Cyprus | D51: Europe | E51: TRUE | G51: 1370750 | J51: 38740000000 | K51: 33890000000 | L51: 28259 | M51: 2022 | N51: 0.31534076 | O51: 0.913 | P51: 81.648 | Q51: 16.215599 | R51: 12.557372 | S51: 45394.156 | T51: 55.2 | U51: 26.7 | V51: 42.8 | W51: 51.8 | X51: 55.6 | Y51: 87.8 | Z51: 8.2 | AA51: 6.5 | AB51: 7.1 | AC51: 15.4 | AD51: 14 | AE51: 62 | AF51: 1.6 | AG51: 160.4 | AH51: 90.6 | AI51: 67.3 | AJ51: 56.5 | AK51: 8.2 | AL51: 25.1 | AM51: 55.4 | AN51: 93.3 | AO51: 5.942
A52: CZ | B52: CZE | C52: Czech Republic | D52: Europe | E52: TRUE | F52: Koruna | G52: 10609200 | H52: -14.6 | I52: 2.2 | J52: 360240000000 | K52: 343210000000 | L52: 33956 | M52: 2022 | N52: 0.2587039 | O52: 0.915 | P52: 79.834 | Q52: 16.793501 | R52: 12.963182 | S52: 45889.014 | T52: 48.2 | U52: 20 | V52: 35.9 | W52: 46.4 | X52: 37.9 | Y52: 94.8 | Z52: 13.6 | AA52: 3.3 | AB52: 3.7 | AC52: 29.9 | AD52: 27.4 | AE52: 111.8 | AF52: 0.9 | AG52: 176.3 | AH52: 97.6 | AI52: 73.4 | AJ52: 75.5 | AK52: 13.6 | AL52: 28.9 | AM52: 34.6 | AN52: 78.7 | AO52: 6.775
A53: CD | B53: COD | C53: DR Congo | D53: Africa | E53: TRUE | G53: 112832000 | J53: 79120000000 | K53: 69340000000 | L53: 701 | M53: 2020 | N53: 0.4467324 | O53: 0.522 | P53: 61.895 | Q53: 10.911474 | R53: 7.3785611 | S53: 1431.0479 | T53: 46.5 | U53: 26.7 | V53: 37.9 | W53: 43.6 | X53: 54.1 | Y53: 27.3 | AO53: 3.469
A54: DK | B54: DNK | C54: Denmark | D54: Europe | E54: TRUE | F54: Krone | G54: 6002510 | H54: 16.6 | I54: 25.4 | J54: 449940000000 | K54: 407090000000 | L54: 74959 | M54: 2022 | N54: 0.29259402 | O54: 0.962 | P54: 81.933 | Q54: 18.70401 | R54: 13.027321 | S54: 76007.857 | T54: 74.1 | U54: 28.8 | V54: 54.3 | W54: 67.6 | X54: 85.1 | Y54: 148.6 | Z54: 6.1 | AA54: 4.6 | AB54: 4.9 | AC54: 21.9 | AD54: 20.5 | AE54: 45.3 | AF54: 2.2 | AG54: 215.1 | AH54: 152.7 | AI54: 74 | AJ54: 78.3 | AK54: 6.1 | AL54: 27.7 | AM54: 20.9 | AN54: 81.2 | AO54: 7.521
A55: DJ | B55: DJI | C55: Djibouti | D55: Africa | E55: TRUE | G55: 1184080 | J55: 4590000000 | K55: 4000000000 | L55: 3874 | M55: 2017 | N55: 0.41586015 | O55: 0.513 | P55: 65.987 | Q55: 6.20735 | R55: 3.950415 | S55: 6367.606
A56: DM | C56: Dominica | D56: North America | E56: TRUE | G56: 65871 | J56: 742000000 | K56: 650870000 | L56: 11264 | O56: 0.761 | P56: 71.132 | Q56: 14.151 | R56: 10.12509 | S56: 16001.126
A57: DO | B57: DOM | C57: Dominican Republic | D57: North America | E57: TRUE | G57: 11520500 | J57: 127830000000 | K57: 121440000000 | L57: 11096 | M57: 2023 | N57: 0.38397565 | O57: 0.776 | P57: 73.72 | Q57: 13.61692 | R57: 9.4445258 | S57: 22023.511 | T57: 34.7 | U57: 10 | V57: 24 | W57: 36.2 | X57: 32.4 | Y57: 37.1 | Z57: 15.2 | AA57: 6.4 | AB57: 5 | AC57: 15.5 | AD57: 19.9 | AE57: 216.4 | AF57: 0.5 | AO57: 5.846
A58: EC | B58: ECU | C58: Ecuador | D58: South America | E58: TRUE | G58: 18289900 | J58: 125680000000 | K58: 118840000000 | L58: 6871 | M58: 2023 | N58: 0.44579554 | O58: 0.777 | P58: 77.392 | Q58: 14.85167 | R58: 8.9700003 | S58: 13986.397 | T58: 29.3 | U58: 8.1 | V58: 20.1 | W58: 32.3 | X58: 24.2 | Y58: 52 | Z58: 11 | AA58: 6.2 | AB58: 5.4 | AC58: 16.3 | AD58: 18.6 | AE58: 132.4 | AF58: 0.8 | AG58: 130.8 | AH58: 53.1 | AI58: 37.4 | AJ58: 78 | AK58: 11 | AL58: 37.1 | AM58: 59.1 | AN58: 94.5 | AO58: 5.965
A59: EG | B59: EGY | C59: Egypt | D59: Africa | E59: TRUE | F59: Pound | G59: 118366000 | H59: -57.9 | I59: -40.8 | J59: 347340000000 | K59: 331590000000 | L59: 2934 | M59: 2021 | N59: 0.28482038 | O59: 0.754 | P59: 71.633 | Q59: 13.127162 | R59: 10.13612 | S59: 16218.135 | T59: 19.6 | U59: 3.9 | V59: 12.8 | W59: 20.1 | X59: 17.6 | Y59: 22.7 | Z59: 20.9 | AA59: 5 | AB59: 5.2 | AC59: 19.9 | AD59: 19.2 | AE59: 355.8 | AF59: 0.3 | AG59: 83.2 | AH59: 23.1 | AI59: 53.1 | AJ59: 47.5 | AK59: 20.9 | AL59: 47.7 | AM59: 82.7 | AN59: 90.8 | AO59: 3.817
A60: SV | B60: SLV | C60: El Salvador | D60: North America | E60: TRUE | G60: 6365500 | J60: 36750000000 | K60: 34020000000 | L60: 5773 | M60: 2023 | N60: 0.39802378 | O60: 0.678 | P60: 72.099 | Q60: 11.11291 | R60: 7.3000002 | S60: 10594.842 | T60: 37.6 | U60: 16.1 | V60: 28.2 | W60: 42.3 | X60: 30.3 | Y60: 35 | Z60: 19.3 | AA60: 6 | AB60: 8.6 | AC60: 16.5 | AD60: 11.7 | AE60: 209.4 | AF60: 0.5 | AO60: 6.492
A61: GQ | B61: GNQ | C61: Equatorial Guinea | D61: Africa | E61: TRUE | G61: 1938430 | J61: 12680000000 | K61: 12120000000 | L61: 6543 | M61: 2022 | N61: 0.38542363 | O61: 0.674 | P61: 63.707 | Q61: 12.491195 | R61: 8.281327 | S61: 12762.468
A62: ER | C62: Eritrea | D62: Africa | E62: TRUE | G62: 3607000 | K62: 2280000000 | L62: 631 | O62: 0.503 | P62: 68.624 | Q62: 7.3366723 | R62: 5.0913644 | S62: 2029.0701
A63: EE | B63: EST | C63: Estonia | D63: Europe | E63: TRUE | G63: 1344230 | J63: 45000000000 | K63: 41290000000 | L63: 33479 | M63: 2022 | N63: 0.32252404 | O63: 0.905 | P63: 79.153 | Q63: 15.96786 | R63: 13.562166 | S63: 40880.93 | T63: 55.9 | U63: 16.1 | V63: 38.5 | W63: 51.2 | X63: 57.8 | Y63: 89.6 | Z63: 11.1 | AA63: 3.3 | AB63: 3.4 | AC63: 29.9 | AD63: 29.1 | AE63: 87.1 | AF63: 1.1 | AG63: 189.8 | AH63: 91.5 | AI63: 76.5 | AJ63: 74.8 | AK63: 11.1 | AL63: 21.4 | AM63: 16.9 | AN63: 71.2 | AO63: 6.417
A64: SZ | B64: SWZ | C64: Eswatini | D64: Africa | E64: TRUE | G64: 1256170 | J64: 5480000000 | K64: 4570000000 | L64: 4365 | M64: 2016 | N64: 0.54579794 | O64: 0.695 | P64: 64.123 | Q64: 15.246044 | R64: 8.6851997 | S64: 9919.0852 | AO64: 3.774
A65: ET | B65: ETH | C65: Ethiopia | D65: Africa | E65: TRUE | G65: 135472000 | J65: 117460000000 | K65: 159750000000 | L65: 867 | M65: 2021 | N65: 0.31141794 | O65: 0.497 | P65: 67.315 | Q65: 9.2176516 | R65: 2.4025398 | S65: 2795.507 | T65: 41.6 | U65: 16.6 | V65: 30.7 | W65: 44.4 | X65: 22.2 | Y65: 13.2 | AO65: 3.898
A66: FK | C66: Falkland Islands | D66: South America | E66: FALSE
A67: FO | C67: Faroe Islands | D67: Europe | E67: FALSE
A68: FJ | B68: FJI | C68: Fiji | D68: Oceania | E68: TRUE | G68: 933154 | J68: 6260000000 | K68: 5440000000 | L68: 6705 | M68: 2019 | N68: 0.30706868 | O68: 0.731 | P68: 67.316 | Q68: 13.84869 | R68: 10.37097 | S68: 12843.159 | T68: 33.3 | U68: 17.1 | V68: 26.2 | W68: 42.7 | X68: 29.9 | Y68: 63.7
A69: FI | B69: FIN | C69: Finland | D69: Europe | E69: TRUE | G69: 5623330 | J69: 303940000000 | K69: 295530000000 | L69: 54051 | M69: 2022 | N69: 0.27925923 | O69: 0.948 | P69: 81.91 | Q69: 19.494089 | R69: 12.979625 | S69: 57067.637 | T69: 64.5 | U69: 21.1 | V69: 45.6 | W69: 64.9 | X69: 67 | Y69: 139.5 | Z69: 7.8 | AA69: 3.1 | AB69: 3.9 | AC69: 31.8 | AD69: 25.3 | AE69: 55.8 | AF69: 1.8 | AG69: 208.3 | AH69: 142.9 | AI69: 73.5 | AJ69: 77.4 | AK69: 7.8 | AL69: 25.1 | AM69: 11.7 | AN69: 54.4 | AO69: 7.736
A70: FR | B70: FRA | C70: France | D70: Europe | E70: TRUE | G70: 66650800 | J70: 3210000000000 | K70: 3050000000000 | L70: 48181 | M70: 2022 | N70: 0.3123691 | O70: 0.92 | P70: 83.325 | Q70: 16.095119 | R70: 11.765668 | S70: 55060.16 | T70: 64.4 | U70: 22 | V70: 46 | W70: 70.1 | X70: 60 | Y70: 119.8 | Z70: 9.9 | AA70: 3.1 | AB70: 3.5 | AC70: 32.7 | AD70: 28.9 | AE70: 69.8 | AF70: 1.4 | AG70: 169.5 | AH70: 122.8 | AI70: 44.4 | AJ70: 77.2 | AK70: 9.9 | AL70: 34.4 | AM70: 43.7 | AN70: 89.9 | AO70: 6.593
A71: GF | C71: French Guiana | D71: South America | E71: FALSE
A72: PF | C72: French Polynesia | D72: Oceania | E72: FALSE | G72: 282465 | K72: 6400000000 | L72: 22651
A73: GA | B73: GAB | C73: Gabon | D73: Africa | E73: TRUE | G73: 2593130 | J73: 20390000000 | K73: 20060000000 | L73: 7863 | M73: 2017 | N73: 0.38024372 | O73: 0.733 | P73: 68.337 | Q73: 12.482759 | R73: 9.686 | S73: 18854.062 | AO73: 5.12
A74: GM | B74: GMB | C74: Gambia | D74: Africa | E74: TRUE | G74: 2822090 | J74: 2770000000 | K74: 2400000000 | L74: 982 | M74: 2020 | N74: 0.38757205 | O74: 0.524 | P74: 65.86 | Q74: 8.9778997 | R74: 4.6747272 | S74: 2812.0176 | AO74: 4.423
A75: GE | B75: GEO | C75: Georgia | D75: Asia | E75: TRUE | G75: 3806670 | J75: 35350000000 | K75: 30540000000 | L75: 9287 | M75: 2023 | N75: 0.34756896 | O75: 0.844 | P75: 74.496 | Q75: 16.754709 | R75: 12.7 | S75: 20752.57 | T75: 31.2 | U75: 12.9 | V75: 23.2 | W75: 30.9 | X75: 34.2 | Y75: 45.4 | Z75: 12 | AA75: 8.1 | AB75: 8.3 | AC75: 12.4 | AD75: 12 | AE75: 158.7 | AF75: 0.6 | AG75: 129.1 | AH75: 46.7 | AI75: 74 | AJ75: 56.4 | AK75: 12 | AL75: 37.1 | AM75: 67.6 | AN75: 88.5 | AO75: 5.4
A76: DE | B76: DEU | C76: Germany | D76: Europe | E76: TRUE | G76: 84075100 | J76: 4740000000000 | K76: 4530000000000 | L76: 56435 | M76: 2020 | N76: 0.3243345 | O76: 0.959 | P76: 81.378 | Q76: 17.309219 | R76: 14.296372 | S76: 64053.221 | T76: 64.7 | U76: 25.4 | V76: 47.6 | W76: 62.1 | X76: 60.8 | Y76: 140.4 | Z76: 8.5 | AA76: 3.6 | AB76: 3.5 | AC76: 27.7 | AD76: 28.8 | AE76: 61.7 | AF76: 1.6 | AG76: 195.2 | AH76: 144.3 | AI76: 60.4 | AJ76: 71.7 | AK76: 8.5 | AL76: 29.6 | AM76: 28.8 | AN76: 82.8 | AO76: 6.753
A77: GH | B77: GHA | C77: Ghana | D77: Africa | E77: TRUE | G77: 35064300 | J77: 88330000000 | K77: 76370000000 | L77: 2519 | M77: 2016 | N77: 0.43508595 | O77: 0.628 | P77: 65.498 | Q77: 11.41846 | R77: 7.1072102 | S77: 6846.3522 | T77: 31.1 | U77: 10.5 | V77: 22.1 | W77: 34.2 | X77: 29 | Y77: 18.3 | AO77: 4.34
A78: GI | C78: Gibraltar | D78: Europe | E78: FALSE
A79: GR | B79: GRC | C79: Greece | D79: Europe | E79: TRUE | G79: 9938840 | J79: 267350000000 | K79: 243500000000 | L79: 26899 | M79: 2022 | N79: 0.333736 | O79: 0.908 | P79: 81.857 | Q79: 20.845501 | R79: 11.553856 | S79: 35760.749 | T79: 51 | U79: 12.8 | V79: 34.4 | W79: 48.6 | X79: 53.9 | Y79: 65.3 | Z79: 13.1 | AA79: 3.6 | AB79: 3.5 | AC79: 27.7 | AD79: 28.5 | AE79: 100.3 | AF79: 1 | AG79: 140.4 | AH79: 66.6 | AI79: 53.6 | AJ79: 58.5 | AK79: 13.1 | AL79: 32.8 | AM79: 49.4 | AN79: 93.1 | AO79: 5.776
A80: GL | C80: Greenland | D80: North America | E80: FALSE | G80: 55745 | K80: 3040000000 | L80: 54547
A81: GD | B81: GRD | C81: Grenada | D81: North America | E81: TRUE | G81: 117303 | J81: 1460000000 | K81: 1320000000 | L81: 12480 | M81: 2018 | N81: 0.4381641 | O81: 0.791 | P81: 75.205 | Q81: 16.577289 | R81: 9.4463993 | S81: 14349.028
A82: GP | C82: Guadeloupe | D82: North America | E82: FALSE
A83: GU | C83: Guam | D83: Oceania | E83: FALSE
A84: GT | B84: GTM | C84: Guatemala | D84: North America | E84: TRUE | F84: Quetzal | G84: 18687900 | H84: -32.7 | I84: -7.1 | J84: 121180000000 | K84: 104450000000 | L84: 6484 | M84: 2023 | N84: 0.45212683 | O84: 0.662 | P84: 72.602 | Q84: 10.67763 | R84: 5.8473001 | S84: 12458.604 | T84: 37.9 | U84: 15.3 | V84: 28 | W84: 42.6 | X84: 34.6 | Y84: 37.8 | AO84: 6.362
A85: GG | C85: Guernsey | D85: Europe | E85: FALSE | T85: 70.2 | U85: 52.5 | V85: 62.5 | W85: 72.4 | X85: 65.7 | Y85: 147.4
A86: GN | B86: GIN | C86: Guinea | D86: Africa | E86: TRUE | G86: 15099700 | J86: 30090000000 | K86: 23010000000 | L86: 1993 | M86: 2018 | N86: 0.29591954 | O86: 0.5 | P86: 60.74 | Q86: 10.393306 | R86: 2.486339 | S86: 3494.3477 | AO86: 4.929
A87: GW | B87: GNB | C87: Guinea-Bissau | D87: Africa | E87: TRUE | G87: 2249520 | J87: 2270000000 | K87: 1840000000 | L87: 1011 | M87: 2021 | N87: 0.33435068 | O87: 0.514 | P87: 64.085 | Q87: 10.635346 | R87: 3.673035 | S87: 2403.0592
A88: GY | C88: Guyana | D88: South America | E88: TRUE | G88: 835986 | J88: 25820000000 | K88: 16680000000 | L88: 30888 | O88: 0.776 | P88: 70.18 | Q88: 13.022058 | R88: 8.7024297 | S88: 46959.252 | T88: 46.9 | U88: 19.8 | V88: 35.1 | W88: 59 | X88: 48.2 | Y88: 61.9
A89: HT | B89: HTI | C89: Haiti | D89: North America | E89: TRUE | G89: 11906100 | J89: 33550000000 | K89: 19840000000 | L89: 2818 | M89: 2012 | N89: 0.60450804 | O89: 0.554 | P89: 64.936 | Q89: 10.896359 | R89: 5.3822999 | S89: 2934.9258
A90: HN | B90: HND | C90: Honduras | D90: North America | E90: TRUE | F90: Lempira | G90: 11005800 | H90: -29 | I90: 0.5 | J90: 38170000000 | K90: 34400000000 | L90: 3468 | M90: 2023 | N90: 0.46826828 | O90: 0.645 | P90: 72.884 | Q90: 10.162206 | R90: 7.5102291 | S90: 6064.7858 | T90: 34.1 | U90: 11 | V90: 24.1 | W90: 38.8 | X90: 30.2 | Y90: 45.3 | AO90: 5.964
A91: HK | C91: Hong Kong | D91: Asia | E91: FALSE | F91: HK$ | G91: 7396080 | H91: -47 | I91: -49.8 | J91: 424000000000 | K91: 380810000000 | L91: 57328 | O91: 0.955 | P91: 85.511 | Q91: 16.895861 | R91: 12.35 | S91: 69435.757 | T91: 72.2 | U91: 57 | V91: 65.6 | W91: 73.9 | X91: 46.8 | Y91: 110.4 | Z91: 28.5 | AA91: 2 | AB91: 2.2 | AC91: 49.3 | AD91: 44.5 | AE91: 207.4 | AF91: 0.5 | AG91: 139 | AH91: 115.5 | AI91: 78.5 | AJ91: 66.5 | AK91: 28.5 | AL91: 41.8 | AM91: 66.5 | AN91: 83.6 | AO91: 5.491
A92: HU | B92: HUN | C92: Hungary | D92: Europe | E92: TRUE | F92: Forint | G92: 9632290 | H92: -25.7 | I92: -8.2 | J92: 237070000000 | K92: 212660000000 | L92: 24612 | M92: 2022 | N92: 0.30222824 | O92: 0.87 | P92: 77.024 | Q92: 15.4694 | R92: 12.331622 | S92: 37236.075 | T92: 42.3 | U92: 13.6 | V92: 29.8 | W92: 40.3 | X92: 39.4 | Y92: 79.5 | Z92: 13.6 | AA92: 3.3 | AB92: 3.6 | AC92: 30.1 | AD92: 28 | AE92: 129.6 | AF92: 0.8 | AG92: 147.1 | AH92: 81.4 | AI92: 66.3 | AJ92: 54.1 | AK92: 13.6 | AL92: 35.5 | AM92: 46.7 | AN92: 79.3 | AO92: 5.915
A93: IS | B93: ISL | C93: Iceland | D93: Europe | E93: TRUE | G93: 398266 | J93: 35310000000 | K93: 31330000000 | L93: 88657 | M93: 2018 | N93: 0.2656501 | O93: 0.972 | P93: 82.691 | Q93: 18.85059 | R93: 13.908926 | S93: 69116.937 | T93: 94.5 | U93: 50.1 | V93: 75.2 | W93: 102.5 | X93: 99.3 | Y93: 120.1 | Z93: 7.7 | AA93: 5.9 | AB93: 6.1 | AC93: 17.1 | AD93: 16.3 | AE93: 88.9 | AF93: 1.1 | AG93: 198 | AH93: 124.3 | AI93: 74.2 | AJ93: 67.9 | AK93: 7.7 | AL93: 21.2 | AM93: 16.7 | AN93: 68.8 | AO93: 7.515
A94: IN | B94: IND | C94: India | D94: Asia | E94: TRUE | F94: Rupee | G94: 1463870000 | H94: -56.2 | I94: -38.5 | J94: 4190000000000 | K94: 3580000000000 | L94: 2860 | M94: 2022 | N94: 0.25514996 | O94: 0.685 | P94: 72.003 | Q94: 12.95454 | R94: 6.8800001 | S94: 9046.7563 | T94: 19 | U94: 4.7 | V94: 12.8 | W94: 21.9 | X94: 15.2 | Y94: 83.8 | Z94: 11.7 | AA94: 2.7 | AB94: 3.2 | AC94: 37 | AD94: 31 | AE94: 126.1 | AF94: 0.8 | AG94: 124.4 | AH94: 85.5 | AI94: 55.8 | AJ94: 65.5 | AK94: 11.7 | AL94: 46.5 | AM94: 72.8 | AN94: 64.5 | AO94: 4.389
A95: ID | B95: IDN | C95: Indonesia | D95: Asia | E95: TRUE | F95: Rupiah | G95: 285721000 | H95: -57 | I95: -41.1 | J95: 1430000000000 | K95: 1370000000000 | L95: 5004 | M95: 2024 | N95: 0.34894395 | O95: 0.728 | P95: 71.146 | Q95: 13.335777 | R95: 8.6972232 | S95: 13700.13 | T95: 24.6 | U95: 8.4 | V95: 17.6 | W95: 32.4 | X95: 14.4 | Y95: 33.3 | Z95: 16.3 | AA95: 6.7 | AB95: 6.5 | AC95: 14.9 | AD95: 15.4 | AE95: 180.8 | AF95: 0.6 | AG95: 101.6 | AH95: 34.1 | AI95: 53.9 | AJ95: 61.2 | AK95: 16.3 | AL95: 43.1 | AM95: 68.1 | AN95: 66.7 | AO95: 5.617
A96: IR | B96: IRN | C96: Iran | D96: Asia | E96: TRUE | G96: 92417700 | J96: 341010000000 | K96: 401600000000 | L96: 3690 | M96: 2023 | N96: 0.35884795 | O96: 0.799 | P96: 77.654 | Q96: 13.968331 | R96: 10.846712 | S96: 16095.772 | T96: 22.7 | U96: 7.7 | V96: 16.2 | W96: 19.9 | X96: 15.1 | Y96: 32 | Z96: 18.7 | AA96: 5.9 | AB96: 6.6 | AC96: 16.9 | AD96: 15 | AE96: 432.6 | AF96: 0.2 | AG96: 86.7 | AH96: 32.8 | AI96: 49.5 | AJ96: 52.7 | AK96: 18.7 | AL96: 46.8 | AM96: 75.3 | AN96: 66.9 | AO96: 5.093
A97: IQ | B97: IRQ | C97: Iraq | D97: Asia | E97: TRUE | G97: 47020800 | J97: 258020000000 | K97: 232110000000 | L97: 5487 | M97: 2023 | N97: 0.2977404 | O97: 0.695 | P97: 72.324 | Q97: 12.359401 | R97: 6.7800463 | S97: 12653.525 | T97: 27.1 | U97: 7 | V97: 18.3 | W97: 27.5 | X97: 22.3 | Y97: 62 | Z97: 8.3 | AA97: 5.4 | AB97: 7 | AC97: 18.5 | AD97: 14.3 | AE97: 84.9 | AF97: 1.2 | AO97: 4.976
A98: IE | B98: IRL | C98: Ireland | D98: Europe | E98: TRUE | G98: 5308040 | J98: 598840000000 | K98: 551390000000 | L98: 112818 | M98: 2022 | N98: 0.2991203 | O98: 0.949 | P98: 82.412 | Q98: 19.184879 | R98: 11.725 | S98: 90884.635 | T98: 66.6 | U98: 44.7 | V98: 57 | W98: 64.7 | X98: 69.6 | Y98: 117.4 | Z98: 6.8 | AA98: 7.7 | AB98: 8 | AC98: 12.9 | AD98: 12.5 | AE98: 51.6 | AF98: 1.9 | AG98: 169.6 | AH98: 122.2 | AI98: 51.4 | AJ98: 51.5 | AK98: 6.8 | AL98: 37.5 | AM98: 34.9 | AN98: 89.8 | AO98: 6.889
A99: IM | C99: Isle of Man | D99: Europe | E99: FALSE | T99: 68.6 | U99: 31.6 | V99: 52.5 | W99: 60.9 | X99: 81.6 | Y99: 123.7
A100: IL | B100: ISR | C100: Israel | D100: Asia | E100: TRUE | F100: Shekel | G100: 9517180 | H100: -1.1 | I100: 8.9 | J100: 583360000000 | K100: 513610000000 | L100: 61296 | M100: 2021 | N100: 0.3789385 | O100: 0.919 | P100: 82.408 | Q100: 14.93416 | R100: 13.534595 | S100: 48050.112 | T100: 69.6 | U100: 28.7 | V100: 51.8 | W100: 65.1 | X100: 75.3 | Y100: 124.2 | Z100: 13.2 | AA100: 2.7 | AB100: 2.8 | AC100: 36.6 | AD100: 35.9 | AE100: 104.4 | AF100: 1 | AG100: 169.5 | AH100: 127.8 | AI100: 68.3 | AJ100: 73.4 | AK100: 13.2 | AL100: 36.8 | AM100: 56.7 | AN100: 93.8 | AO100: 7.234
...
